Workbook
Name CfgLoc: Configs!$D$6:$D$25
Name CfgMix: Configs!$G$6:$G$25
Name CfgName: Configs!$C$6:$C$25
Name CfgProp: Configs!$E$6:$E$25
Name CfgRoast: Configs!$F$6:$F$25
Name Circ: Cover!$D$29
Name Lakh: Inputs!$D$27
Name LocList: Locations!$D$5:$G$5
Name MixCheck: Sourcing!$F$20:$I$20
Name MixList: Sourcing!$F$14:$I$14
Name PropList: Inputs!$F$167:$H$167
Name RoastList: Sourcing!$F$41:$H$41
Name ScnList: Inputs!$F$168:$I$168
Name TaxRate: Inputs!$D$28

Sheet Cover
B1: Specialty Café, Ahmedabad: 3-Statement & FCFF DCF Model
B2: Location × premises (rent/own) × roasting × bean-mix decision model. Prepared October 2026. All figures in ₹ lakh unless stated (1 lakh = ₹1,00,000).
B3: ="Model running: "&Inputs!$D$23 -> Model running: Prahladnagar | Rent | Toll roasting | Specialty mix | Base case
B5: Contents
B6: Dashboard | C6: Key outputs, charts, scenario and premises comparison
B7: Inputs | C7: Configuration switches, Best/Base/Worst drivers, all operating assumptions
B8: Locations | C8: Library of four Ahmedabad sites: rent, area, footfall, ticket, capex
B9: Sourcing | C9: Green-coffee prices, bean mixes, cost per kg by roasting route
B10: Capex | C10: Equipment & fit-out list, property purchase, sources & uses of funds
B11: Model | C11: Income statement, cash flow, balance sheet and supporting schedules
B12: DCF | C12: FCFF, WACC, terminal value, NPV, IRR, equity IRR, payback
B13: Scenarios | C13: Override panel and live data tables (scenarios, sensitivities, tornado)
B14: Configs | C14: 19 pre-defined configurations compared side by side (editable)
B15: Sources | C15: Where the assumptions come from
B17: Model checks
B18: Balance sheet balances (all years) | D18: =IF(SUMPRODUCT(ABS(Model!$F$76:$P$76))<0.01,"OK","ERROR") -> OK
B19: Cash never negative | D19: =IF(MIN(Model!$F$61:$P$61)>=-0.001,"OK","ERROR") -> OK
B20: Sources of funds = uses of funds | D20: =IF(ABS(Capex!$G$53-Capex!$G$58)<0.001,"OK","ERROR") -> OK
B21: Every bean mix adds up to 100% | D21: =IF(SUMPRODUCT(ABS(MixCheck-1))<0.0001,"OK","ERROR") -> OK
B22: Revenue mix shares between 0% and 100% | D22: =IF(AND(Inputs!$D$77>=0,Inputs!$D$77<=1),"OK","ERROR") -> OK
B23: WACC above terminal growth | D23: =IF(DCF!$D$41>DCF!$D$42,"OK","ERROR") -> OK
B24: Seating capacity does not cap demand | D24: =IF(SUMPRODUCT(--(Model!$F$83:$P$83>Model!$F$84:$P$84+0.001))=0,"OK","INFO: capacity binds") -> OK
B25: Scenarios-sheet overrides switched off | D25: =IF(AND(Scenarios!$D$6=0,Scenarios!$D$7=0,Scenarios!$D$8=0,Scenarios!$D$9=0,Scenarios!$D$10=0,Scenarios!$D$11=0,Scenarios!$D$13=1,Scenarios!$D$14=1,Scenarios!$D$15=1,Scenarios!$D$16=1,Scenarios!$D$17=1,Scenarios!$D$18=1,Scenarios!$D$19=0,Scenarios!$D$20=0,Scenarios!$D$21=0,Scenarios!$D$22=0,Scenarios!$D$12=0),"OK","INFO: overrides active") -> OK
B26: Overall model status | D26: =IF(COUNTIF(D18:D23,"OK")=6,"ALL CHECKS OK","REVIEW") -> ALL CHECKS OK
B28: Switches
B29: Circularity switch (1 = interest on average balances) | C29: 0 = interest on opening balances (no circular reference). 1 needs iterative calculation (enabled in this file). | D29: 0
B31: Conventions
B32: Blue on cream | C32: Hard-coded input: change these
B33: Black | C33: Formula on the same sheet
B34: Green | C34: Formula linking to another sheet
B35: Units | C35: ₹ lakh unless the Units column says otherwise; rupee inputs are in ₹
B36: Timeline | C36: Y0 = FY27 (fit-out, pre-opening; ends 31 Mar 2027). Y1-Y10 = FY28-FY37. Annual periods, fiscal year to 31 March
B37: Signs | C37: Income statement costs and cash outflows are shown as negatives
B38: Tax | C38: Corporate tax under s.115BAA, 25.168% incl. surcharge & cess; WDV tax depreciation; losses carried forward
B39: Leases | C39: Rent is an operating expense (Indian GAAP / AS for an unlisted SME, no Ind AS 116 right-of-use asset)
B41: How to use
B42: 1. Inputs sheet, section 1: pick Location, Premises (Rent / Own), Roasting route, Bean mix and Scenario from the drop-downs.
B43: 2. Read the result on the Dashboard; every statement and schedule is on the Model and DCF sheets.
B44: 3. Change any blue cell (Inputs, Locations, Sourcing, Capex, Configs) to test your own numbers.
B45: 4. Scenarios sheet: live data tables re-run the whole model for every scenario, configuration and sensitivity. Leave its override cells at their defaults.
B46: 5. Configs sheet: edit or add combinations; their results update automatically.
B47: 6. If Excel is set to 'Automatic except data tables', press F9 to refresh the tables.

Sheet Dashboard
B1: Dashboard
B2: Outputs for the configuration and scenario chosen on Inputs. ₹ lakh unless stated.
B3: ="Model running: "&Inputs!$D$23 -> Model running: Prahladnagar | Rent | Toll roasting | Specialty mix | Base case
B5: Selected configuration
B6: Location | D6: =Inputs!$F$15 -> Prahladnagar
B7: Premises | D7: =Inputs!$F$16 -> Rent
B8: Roasting route | D8: =Inputs!$F$17 -> Toll roasting
B9: Bean mix | D9: =Inputs!$F$18 -> Specialty
B10: Scenario | D10: =Inputs!$F$19 -> Base
B12: Key outputs
B13: Total capital requirement | D13: =DCF!$D$80 -> 101.228 | F13: Payback from opening | J13: =DCF!$D$76 -> 4.7237112
B14: Promoter equity | D14: =DCF!$D$81 -> 68.028 | F14: Discounted payback | J14: =DCF!$D$77 -> 8.1954564
B15: Term loan | D15: =DCF!$D$82 -> 33.2 | F15: Revenue Y3 | J15: =DCF!$D$84 -> 177.8112
B16: WACC | D16: =DCF!$D$41 -> 0.161554 | F16: EBITDA Y3 | J16: =DCF!$D$85 -> 33.683883
B17: Cost of equity | D17: =DCF!$D$37 -> 0.20022526 | F17: EBITDA margin Y3 | J17: =DCF!$D$86 -> 0.18943623
B18: Project NPV | D18: =DCF!$D$61 -> 89.598107 | F18: Bills per day Y3 | J18: =DCF!$D$88 -> 140
B19: Project IRR | D19: =DCF!$D$64 -> 0.28636431 | F19: Break-even bills per day Y3 | J19: =DCF!$D$89 -> 95.968282
B20: Equity IRR | D20: =DCF!$D$68 -> 0.3293081 | F20: Margin of safety Y3 | J20: =DCF!$D$90 -> 0.31451227
B21: Equity NPV at cost of equity | D21: =DCF!$D$69 -> 65.839478 | F21: Peak cash-credit draw | J21: =DCF!$D$97 -> 0
B22: Equity multiple | D22: =DCF!$D$70 -> 8.8873609 | F22: Minimum DSCR (Y2 on) | J22: =DCF!$D$98 -> 1.851354
B23: Terminal value share of value | D23: =DCF!$D$62 -> 0.42342231 | F23: Pre-tax ROCE Y5 | J23: =DCF!$D$101 -> 0.73062017
B24: Implied exit EV/EBITDA | D24: =DCF!$D$56 -> 5.5955523 | F24: Cash lost if shut after Y3 | J24: =DCF!$D$99 -> 19.628082
B26: Financial summary (₹ lakh)
B27: ₹ lakh | F27: =Model!F5 -> 2027 | G27: =Model!G5 -> 2028 | H27: =Model!H5 -> 2029 | I27: =Model!I5 -> 2030 | J27: =Model!J5 -> 2031 | K27: =Model!K5 -> 2032 | L27: =Model!L5 -> 2033 | M27: =Model!M5 -> 2034 | ... P27: =Model!P5 -> 2037
B28: Bills per day | C28: # | F28: =Model!F85 -> 0 | G28: =Model!G85 -> 91 | H28: =Model!H85 -> 119 | I28: =Model!I85 -> 140 | J28: =Model!J85 -> 143.5 | K28: =Model!K85 -> 147.0875 | L28: =Model!L85 -> 150.76469 | M28: =Model!M85 -> 154.5338 | ... P28: =Model!P85 -> 166.41601
B29: Average bill (₹) | C29: ₹ | F29: =Model!F89 -> 0 | G29: =Model!G89 -> 320 | H29: =Model!H89 -> 336 | I29: =Model!I89 -> 352.8 | J29: =Model!J89 -> 370.44 | K29: =Model!K89 -> 388.962 | L29: =Model!L89 -> 408.4101 | M29: =Model!M89 -> 428.83061 | ... P29: =Model!P89 -> 496.42503
B30: Revenue | C30: ₹ lakh | F30: =Model!F16 -> 0 | G30: =Model!G16 -> 104.832 | H30: =Model!H16 -> 143.9424 | I30: =Model!I16 -> 177.8112 | J30: =Model!J16 -> 191.3693 | K30: =Model!K16 -> 205.96121 | L30: =Model!L16 -> 221.66576 | M30: =Model!M16 -> 238.56777 | ... P30: =Model!P16 -> 297.40705
B31: Gross margin | C31: % | F31: =Model!F20 -> 0 | G31: =Model!G20 -> 0.69758569 | H31: =Model!H20 -> 0.69919187 | I31: =Model!I20 -> 0.70076745 | J31: =Model!J20 -> 0.70231499 | K31: =Model!K20 -> 0.70382976 | L31: =Model!L20 -> 0.70531469 | M31: =Model!M20 -> 0.70677233 | ... P31: =Model!P20 -> 0.71098601
B32: EBITDA | C32: ₹ lakh | F32: =Model!F29 -> -11.0545 | G32: =Model!G29 -> -3.722047 | H32: =Model!H29 -> 17.701906 | I32: =Model!I29 -> 33.683883 | J32: =Model!J29 -> 36.555685 | K32: =Model!K29 -> 39.61794 | L32: =Model!L29 -> 42.879726 | M32: =Model!M29 -> 46.350071 | ... P32: =Model!P29 -> 58.095121
B33: EBITDA margin | C33: % | F33: =Model!F30 -> 0 | G33: =Model!G30 -> -0.035504875 | H33: =Model!H30 -> 0.1229791 | I33: =Model!I30 -> 0.18943623 | J33: =Model!J30 -> 0.19102168 | K33: =Model!K30 -> 0.19235632 | L33: =Model!L30 -> 0.19344317 | M33: =Model!M30 -> 0.19428471 | ... P33: =Model!P30 -> 0.19533875
B34: Profit after tax | C34: ₹ lakh | F34: =Model!F38 -> -11.0545 | G34: =Model!G38 -> -14.924471 | H34: =Model!H38 -> 6.6158733 | I34: =Model!I38 -> 22.001296 | J34: =Model!J38 -> 20.077347 | K34: =Model!K38 -> 23.411655 | L34: =Model!L38 -> 26.600993 | M34: =Model!M38 -> 27.84088 | ... P34: =Model!P38 -> 45.306616
B35: Cash from operations | C35: ₹ lakh | F35: =Model!F46 -> -11.0545 | G35: =Model!G46 -> -7.8165266 | H35: =Model!H46 -> 14.469085 | I35: =Model!I46 -> 30.057111 | J35: =Model!J46 -> 28.627479 | K35: =Model!K46 -> 31.921775 | L35: =Model!L46 -> 35.699186 | M35: =Model!M46 -> 39.034682 | ... P35: =Model!P46 -> 51.050829
B36: Capex | C36: ₹ lakh | F36: =Model!F47 -> -66.465 | G36: =Model!G47 -> -1.57248 | H36: =Model!H47 -> -2.159136 | I36: =Model!I47 -> -2.667168 | J36: =Model!J47 -> -2.8705396 | K36: =Model!K47 -> -3.0894182 | L36: =Model!L47 -> -14.816306 | M36: =Model!M47 -> -3.5785165 | ... P36: =Model!P47 -> -4.4611058
B37: Free cash flow to firm | C37: ₹ lakh | F37: =DCF!F24 -> -82.1195 | G37: =DCF!G24 -> -6.5013466 | H37: =DCF!H24 -> 15.108369 | I37: =DCF!I24 -> 27.336694 | J37: =DCF!J24 -> 25.967086 | K37: =DCF!K24 -> 27.923707 | L37: =DCF!L24 -> 18.763378 | M37: =DCF!M24 -> 32.71158 | ... P37: =DCF!P24 -> 40.344655
B38: Cumulative FCFF | C38: ₹ lakh | F38: =DCF!F72 -> -82.1195 | G38: =DCF!G72 -> -88.620847 | H38: =DCF!H72 -> -73.512477 | I38: =DCF!I72 -> -46.175784 | J38: =DCF!J72 -> -20.208698 | K38: =DCF!K72 -> 7.7150088 | L38: =DCF!L72 -> 26.478386 | M38: =DCF!M72 -> 59.189967 | ... P38: =DCF!P72 -> 172.24732
B39: Closing cash | C39: ₹ lakh | F39: =Model!F61 -> 19.1085 | G39: =Model!G61 -> 3.0794934 | H39: =Model!H61 -> 8.7494423 | I39: =Model!I61 -> 29.499385 | J39: =Model!J61 -> 48.616324 | K39: =Model!K61 -> 70.808681 | L39: =Model!L61 -> 91.691561 | M39: =Model!M61 -> 127.14773 | ... P39: =Model!P61 -> 255.22602
B40: Debt (term loan + cash credit) | C40: ₹ lakh | F40: =Model!F203+Model!F209 -> 33.2 | G40: =Model!G203+Model!G209 -> 26.56 | H40: =Model!H203+Model!H209 -> 19.92 | I40: =Model!I203+Model!I209 -> 13.28 | J40: =Model!J203+Model!J209 -> 6.64 | K40: =Model!K203+Model!K209 -> 0 | L40: =Model!L203+Model!L209 -> 0 | M40: =Model!M203+Model!M209 -> 0 | ... P40: =Model!P203+Model!P209 -> 0
B41: Shareholders' equity | C41: ₹ lakh | F41: =Model!F74 -> 56.9735 | G41: =Model!G74 -> 42.049029 | H41: =Model!H74 -> 48.664903 | I41: =Model!I74 -> 70.666199 | J41: =Model!J74 -> 90.743546 | K41: =Model!K74 -> 114.1552 | L41: =Model!L74 -> 140.75619 | M41: =Model!M74 -> 168.59707 | ... P41: =Model!P74 -> 284.20371
B43: Scenario analysis (from Scenarios T1)
B44: Scenario | F44: NPV | G44: Project IRR | H44: Equity IRR | I44: Payback | J44: Y3 revenue | K44: Y3 EBITDA % | L44: Break-even bills | M44: Capital need
B45: Best | F45: =Scenarios!$D$49 -> 0 | G45: =Scenarios!$E$49 -> 0 | H45: =Scenarios!$F$49 -> 0 | I45: =Scenarios!$H$49 -> 0 | J45: =Scenarios!$K$49 -> 0 | K45: =Scenarios!$L$49 -> 0 | L45: =Scenarios!$M$49 -> 0 | M45: =Scenarios!$J$49 -> 0
B46: Base | F46: =Scenarios!$D$50 -> 0 | G46: =Scenarios!$E$50 -> 0 | H46: =Scenarios!$F$50 -> 0 | I46: =Scenarios!$H$50 -> 0 | J46: =Scenarios!$K$50 -> 0 | K46: =Scenarios!$L$50 -> 0 | L46: =Scenarios!$M$50 -> 0 | M46: =Scenarios!$J$50 -> 0
B47: Worst | F47: =Scenarios!$D$51 -> 0 | G47: =Scenarios!$E$51 -> 0 | H47: =Scenarios!$F$51 -> 0 | I47: =Scenarios!$H$51 -> 0 | J47: =Scenarios!$K$51 -> 0 | K47: =Scenarios!$L$51 -> 0 | L47: =Scenarios!$M$51 -> 0 | M47: =Scenarios!$J$51 -> 0
B49: Rent vs own, by location (from Scenarios T2)
B50: Location | F50: NPV Rent | G50: NPV Own | H50: IRR Rent | I50: IRR Own | J50: Eq. IRR Rent | K50: Eq. IRR Own | L50: Capital Rent | M50: Capital Own
B51: Prahladnagar | F51: =Scenarios!$D$57 -> 0 | G51: =Scenarios!$E$57 -> 0 | H51: =Scenarios!$D$64 -> 0 | I51: =Scenarios!$E$64 -> 0 | J51: =Scenarios!$D$71 -> 0 | K51: =Scenarios!$E$71 -> 0 | L51: =Scenarios!$D$78 -> 0 | M51: =Scenarios!$E$78 -> 0
B52: Sindhu Bhavan Road | F52: =Scenarios!$D$58 -> 0 | G52: =Scenarios!$E$58 -> 0 | H52: =Scenarios!$D$65 -> 0 | I52: =Scenarios!$E$65 -> 0 | J52: =Scenarios!$D$72 -> 0 | K52: =Scenarios!$E$72 -> 0 | L52: =Scenarios!$D$79 -> 0 | M52: =Scenarios!$E$79 -> 0
B53: GIFT City | F53: =Scenarios!$D$59 -> 0 | G53: =Scenarios!$E$59 -> 0 | H53: =Scenarios!$D$66 -> 0 | I53: =Scenarios!$E$66 -> 0 | J53: =Scenarios!$D$73 -> 0 | K53: =Scenarios!$E$73 -> 0 | L53: =Scenarios!$D$80 -> 0 | M53: =Scenarios!$E$80 -> 0
B54: Sanand | F54: =Scenarios!$D$60 -> 0 | G54: =Scenarios!$E$60 -> 0 | H54: =Scenarios!$D$67 -> 0 | I54: =Scenarios!$E$67 -> 0 | J54: =Scenarios!$D$74 -> 0 | K54: =Scenarios!$E$74 -> 0 | L54: =Scenarios!$D$81 -> 0 | M54: =Scenarios!$E$81 -> 0
B56: Charts

Sheet Inputs
B1: Inputs & Drivers
B2: Blue cells are inputs. Rupee inputs in ₹ (not lakh). Driver rows marked Live are picked by the Scenario switch.
B3: ="Model running: "&$D$23 -> Model running: Prahladnagar | Rent | Toll roasting | Specialty mix | Base case
B5: ₹ lakh unless stated | C5: Units | D5: Value | F5: =$D$26 -> 2027 | G5: =F5+1 -> 2028 | H5: =G5+1 -> 2029 | I5: =H5+1 -> 2030 | J5: =I5+1 -> 2031 | K5: =J5+1 -> 2032 | L5: =K5+1 -> 2033 | M5: =L5+1 -> 2034 | N5: =M5+1 -> 2035 | ... P5: =O5+1 -> 2037
B6: Period (Y0 = pre-opening fit-out year) | F6: =F5-$D$26 -> 0 | G6: =G5-$D$26 -> 1 | H6: =H5-$D$26 -> 2 | I6: =I5-$D$26 -> 3 | J6: =J5-$D$26 -> 4 | K6: =K5-$D$26 -> 5 | L6: =L5-$D$26 -> 6 | M6: =M5-$D$26 -> 7 | ... P6: =P5-$D$26 -> 10
B7: 1. Configuration: choose what to model
B8: Location | C8: list | D8: Prahladnagar | F8: Prahladnagar (base case), Sindhu Bhavan Road, GIFT City, Sanand: see Locations
B9: Premises | C9: list | D9: Rent | F9: Rent a unit, or buy it (60% funded by a loan against property)
B10: Coffee roasting route | C10: list | D10: Toll roasting | F10: Buy roasted beans / toll-roast your own green coffee / own 3 kg roaster
B11: Bean mix | C11: list | D11: Specialty | F11: Value / Specialty / Premium / Custom blends: see Sourcing
B12: Scenario | C12: list | D12: Base | F12: Best / Base / Worst drivers below
B14: Active configuration (after any Scenarios-sheet overrides)
B15: Location (index) | C15: # | D15: =IF(Scenarios!$D$8>0,Scenarios!$D$8,IF(Scenarios!$D$7>0,MATCH(INDEX(CfgLoc,Scenarios!$D$7),LocList,0),MATCH($D$8,LocList,0))) -> 1 | F15: =INDEX(LocList,$D$15) -> Prahladnagar
B16: Premises (index) | C16: # | D16: =IF(Scenarios!$D$9>0,Scenarios!$D$9,IF(Scenarios!$D$7>0,MATCH(INDEX(CfgProp,Scenarios!$D$7),PropList,0),MATCH($D$9,PropList,0))) -> 1 | F16: =INDEX(PropList,$D$16) -> Rent
B17: Roasting route (index) | C17: # | D17: =IF(Scenarios!$D$10>0,Scenarios!$D$10,IF(Scenarios!$D$7>0,MATCH(INDEX(CfgRoast,Scenarios!$D$7),RoastList,0),MATCH($D$10,RoastList,0))) -> 2 | F17: =INDEX(RoastList,$D$17) -> Toll roasting
B18: Bean mix (index) | C18: # | D18: =IF(Scenarios!$D$11>0,Scenarios!$D$11,IF(Scenarios!$D$7>0,MATCH(INDEX(CfgMix,Scenarios!$D$7),MixList,0),MATCH($D$11,MixList,0))) -> 2 | F18: =INDEX(MixList,$D$18) -> Specialty
B19: Scenario (index) | C19: # | D19: =IF(Scenarios!$D$6>0,Scenarios!$D$6,MATCH($D$12,ScnList,0)) -> 2 | F19: =INDEX(ScnList,$D$19) -> Base
B20: Owned premises flag | C20: 1/0 | D20: =IF($D$16=2,1,0) -> 0
B21: In-house roastery flag | C21: 1/0 | D21: =IF($D$17=3,1,0) -> 0
B22: Own-label beans flag (toll or in-house) | C22: 1/0 | D22: =IF($D$17>=2,1,0) -> 1
B23: Configuration label | C23: text | D23: =$F$15&" | "&$F$16&" | "&$F$17&" | "&$F$18&" mix | "&$F$19&" case" -> Prahladnagar | Rent | Toll roasting | Specialty mix | Base case
B25: 2. General
B26: Year 0 (fit-out year) ends 31 March | C26: FY | D26: 2027 | F26: Y0 = FY2026-27: lease/purchase, fit-out, hiring. Café opens 1 April 2027 (Y1)
B27: Rupees per lakh | C27: ₹ | D27: 100000
B28: Corporate tax rate (s.115BAA) | C28: % | D28: 0.25168 | F28: 22% + 10% surcharge + 4% cess = 25.168%; no MAT under 115BAA
B30: 3. Scenario drivers: Best / Base / Worst (Live row = selected scenario)
B31: Ramp-up (% of steady-state bills)
B32: Best | C32: % | G32: 0.8 | H32: 0.95 | I32: 1 | J32: 1 | K32: 1 | L32: 1 | M32: 1 | N32: 1 | O32: 1 | P32: 1
B33: Base | C33: % | G33: 0.65 | H33: 0.85 | I33: 1 | J33: 1 | K33: 1 | L33: 1 | M33: 1 | N33: 1 | O33: 1 | P33: 1
B34: Worst | C34: % | G34: 0.5 | H34: 0.7 | I34: 0.88 | J34: 0.95 | K34: 0.95 | L34: 0.95 | M34: 0.95 | N34: 0.95 | O34: 0.95 | P34: 0.95
B35: Live | C35: % | G35: =CHOOSE($D$19,G32,G33,G34) -> 0.65 | H35: =CHOOSE($D$19,H32,H33,H34) -> 0.85 | I35: =CHOOSE($D$19,I32,I33,I34) -> 1 | J35: =CHOOSE($D$19,J32,J33,J34) -> 1 | K35: =CHOOSE($D$19,K32,K33,K34) -> 1 | L35: =CHOOSE($D$19,L32,L33,L34) -> 1 | M35: =CHOOSE($D$19,M32,M33,M34) -> 1 | N35: =CHOOSE($D$19,N32,N33,N34) -> 1 | ... P35: =CHOOSE($D$19,P32,P33,P34) -> 1
B36: Menu price increase
B37: Best | C37: % p.a. | G37: 0 | H37: 0.06 | I37: 0.06 | J37: 0.06 | K37: 0.06 | L37: 0.06 | M37: 0.06 | N37: 0.06 | O37: 0.06 | P37: 0.06
B38: Base | C38: % p.a. | G38: 0 | H38: 0.05 | I38: 0.05 | J38: 0.05 | K38: 0.05 | L38: 0.05 | M38: 0.05 | N38: 0.05 | O38: 0.05 | P38: 0.05
B39: Worst | C39: % p.a. | G39: 0 | H39: 0.035 | I39: 0.035 | J39: 0.035 | K39: 0.035 | L39: 0.035 | M39: 0.035 | N39: 0.035 | O39: 0.035 | P39: 0.035
B40: Live | C40: % p.a. | G40: =CHOOSE($D$19,G37,G38,G39) -> 0 | H40: =CHOOSE($D$19,H37,H38,H39) -> 0.05 | I40: =CHOOSE($D$19,I37,I38,I39) -> 0.05 | J40: =CHOOSE($D$19,J37,J38,J39) -> 0.05 | K40: =CHOOSE($D$19,K37,K38,K39) -> 0.05 | L40: =CHOOSE($D$19,L37,L38,L39) -> 0.05 | M40: =CHOOSE($D$19,M37,M38,M39) -> 0.05 | N40: =CHOOSE($D$19,N37,N38,N39) -> 0.05 | ... P40: =CHOOSE($D$19,P37,P38,P39) -> 0.05
B41: Volume growth after ramp (Y4+)
B42: Best | C42: % p.a. | G42: 0 | H42: 0 | I42: 0 | J42: 0.04 | K42: 0.04 | L42: 0.04 | M42: 0.04 | N42: 0.04 | O42: 0.04 | P42: 0.04
B43: Base | C43: % p.a. | G43: 0 | H43: 0 | I43: 0 | J43: 0.025 | K43: 0.025 | L43: 0.025 | M43: 0.025 | N43: 0.025 | O43: 0.025 | P43: 0.025
B44: Worst | C44: % p.a. | G44: 0 | H44: 0 | I44: 0 | J44: 0.005 | K44: 0.005 | L44: 0.005 | M44: 0.005 | N44: 0.005 | O44: 0.005 | P44: 0.005
B45: Live | C45: % p.a. | G45: =CHOOSE($D$19,G42,G43,G44) -> 0 | H45: =CHOOSE($D$19,H42,H43,H44) -> 0 | I45: =CHOOSE($D$19,I42,I43,I44) -> 0 | J45: =CHOOSE($D$19,J42,J43,J44) -> 0.025 | K45: =CHOOSE($D$19,K42,K43,K44) -> 0.025 | L45: =CHOOSE($D$19,L42,L43,L44) -> 0.025 | M45: =CHOOSE($D$19,M42,M43,M44) -> 0.025 | N45: =CHOOSE($D$19,N42,N43,N44) -> 0.025 | ... P45: =CHOOSE($D$19,P42,P43,P44) -> 0.025
B46: Green-coffee price index (Oct 2026 = 1.00)
B47: Best | C47: x | G47: 0.9 | H47: 0.927 | I47: 0.9548 | J47: 0.9835 | K47: 1.013 | L47: 1.0433 | M47: 1.0746 | N47: 1.1069 | O47: 1.1401 | P47: 1.1743
B48: Base | C48: x | G48: 1 | H48: 1.03 | I48: 1.0609 | J48: 1.0927 | K48: 1.1255 | L48: 1.1593 | M48: 1.1941 | N48: 1.2299 | O48: 1.2668 | P48: 1.3048
B49: Worst | C49: x | G49: 1.25 | H49: 1.2875 | I49: 1.3261 | J49: 1.3659 | K49: 1.4069 | L49: 1.4491 | M49: 1.4926 | N49: 1.5373 | O49: 1.5835 | P49: 1.631
B50: Live | C50: x | G50: =CHOOSE($D$19,G47,G48,G49) -> 1 | H50: =CHOOSE($D$19,H47,H48,H49) -> 1.03 | I50: =CHOOSE($D$19,I47,I48,I49) -> 1.0609 | J50: =CHOOSE($D$19,J47,J48,J49) -> 1.0927 | K50: =CHOOSE($D$19,K47,K48,K49) -> 1.1255 | L50: =CHOOSE($D$19,L47,L48,L49) -> 1.1593 | M50: =CHOOSE($D$19,M47,M48,M49) -> 1.1941 | N50: =CHOOSE($D$19,N47,N48,N49) -> 1.2299 | ... P50: =CHOOSE($D$19,P47,P48,P49) -> 1.3048
B51: Wholesale ramp-up (in-house roastery only)
B52: Share of mature wholesale volume | C52: % | G52: 0.3 | H52: 0.6 | I52: 1 | J52: 1 | K52: 1 | L52: 1 | M52: 1 | N52: 1 | O52: 1 | P52: 1
B54: Single-value drivers | C54: Units | D54: Live | F54: Best | G54: Base | H54: Worst
B55: Footfall factor on steady-state bills | C55: x | D55: =CHOOSE($D$19,$F$55,$G$55,$H$55) -> 1 | F55: 1.15 | G55: 1 | H55: 0.82
B56: Capex overrun | C56: % | D56: =CHOOSE($D$19,$F$56,$G$56,$H$56) -> 0.05 | F56: 0 | G56: 0.05 | H56: 0.15
B57: Wholesale beans at maturity (in-house only) | C57: kg/mth | D57: =CHOOSE($D$19,$F$57,$G$57,$H$57) -> 150 | F57: 250 | G57: 150 | H57: 60
B59: 4. Revenue, menu & capacity
B60: Beverages share of café revenue | C60: % | D60: 0.62
B61: Retail beans share (bought-in bags) | C61: % | D61: 0.06
B62: Extra retail share with own-label beans | C62: % | D62: 0.02 | F62: Applies to toll and in-house routes
B63: Average beverage price (FY28) | C63: ₹ | D63: 220 | F63: Used only to convert beverage sales into cups
B64: Beverages that contain coffee | C64: % | D64: 0.85
B65: Coffee per coffee beverage | C65: g | D65: 18 | F65: Double shot 18 g; filter 15-18 g
B66: Milk, syrups, sugar & garnish per beverage | C66: ₹ | D66: 24
B67: Takeaway share of bills (needs packaging) | C67: % | D67: 0.25
B68: Packaging per takeaway/delivery bill | C68: ₹ | D68: 15
B69: Food cost as % of food sales | C69: % | D69: 0.38
B70: Gross margin on bought-in retail bags | C70: % | D70: 0.3
B71: Wholesale selling & delivery cost | C71: % of sales | D71: 0.08
B72: Wholesale volume growth after Y3 | C72: % p.a. | D72: 0.05
B73: Food, packaging & supplies inflation | C73: % p.a. | D73: 0.05
B74: Maximum seat turns per day (capacity cap) | C74: x | D74: 6 | F74: Dine-in bills per seat per day at full capacity
B75: Derived (do not edit)
B76: Retail beans share, active route | C76: % | D76: =$D$61+$D$22*$D$62 -> 0.08
B77: Food share of café revenue | C77: % | D77: =1-$D$60-$D$76 -> 0.3
B78: Beverages per bill | C78: # | D78: =Locations!$H$14*$D$60/$D$63 -> 0.90181818
B80: 5. People
B81: Role | C81: Headcount | D81: Monthly salary ₹ | F81: Roastery only | G81: Monthly ₹
B82: Café manager | C82: 1 | D82: 45000 | F82: 0 | G82: =C82*D82 -> 45000
B83: Head barista | C83: 1 | D83: 30000 | F83: 0 | G83: =C83*D83 -> 30000
B84: Baristas | C84: 4 | D84: 19000 | F84: 0 | G84: =C84*D84 -> 76000
B85: Kitchen lead | C85: 1 | D85: 28000 | F85: 0 | G85: =C85*D85 -> 28000
B86: Kitchen assistants | C86: 2 | D86: 16000 | F86: 0 | G86: =C86*D86 -> 32000
B87: Service staff | C87: 3 | D87: 15000 | F87: 0 | G87: =C87*D87 -> 45000
B88: Housekeeping & dishwash | C88: 2 | D88: 13500 | F88: 0 | G88: =C88*D88 -> 27000
B89: Roaster & wholesale (in-house only) | C89: 1 | D89: 32000 | F89: 1 | G89: =C89*D89 -> 32000
B90: Café roster, monthly | C90: ₹ | D90: =SUMPRODUCT($C$82:$C$89,$D$82:$D$89,1-$F$82:$F$89) -> 283000
B91: Roastery roster, monthly | C91: ₹ | D91: =SUMPRODUCT($C$82:$C$89,$D$82:$D$89,$F$82:$F$89) -> 32000
B92: PF, ESI, bonus, meals & uniforms | C92: % of salary | D92: 0.15
B93: Annual wage increase | C93: % p.a. | D93: 0.08 | F93: Gujarat minimum wage ₹13,325-13,897/month from April 2026
B94: Extra staff per 1% bills above steady state | C94: % | D94: 0.5
B95: Active monthly payroll (location staffing factor applied) | C95: ₹ | D95: =$D$90*Locations!$H$18+$D$21*$D$91 -> 283000
B97: 6. Operating costs
B98: Electricity use | C98: kWh/sqft/mth | D98: 5
B99: Electricity tariff, all-in (FY28) | C99: ₹/kWh | D99: 9.5 | F99: Torrent Power non-RGP: 455 paise/unit energy + fixed + FPPPA + duty
B100: Tariff increase | C100: % p.a. | D100: 0.04
B101: LPG/PNG, water & cleaning supplies | C101: ₹/mth | D101: 15000
B102: Marketing, launch year | C102: % of revenue | D102: 0.05
B103: Marketing, later years | C103: % of revenue | D103: 0.03
B104: Repairs & maintenance | C104: % of revenue | D104: 0.015
B105: Equipment AMC (espresso, grinders, RO) | C105: ₹/yr | D105: 60000
B106: Roaster AMC & afterburner service | C106: ₹/yr | D106: 60000
B107: Aggregator commission incl. GST & fees | C107: % of delivery sales | D107: 0.25 | F107: Swiggy/Zomato effective 24-30% incl. discounts
B108: Card/UPI processing | C108: % of dine-in sales | D108: 0.007
...

Sheet Locations
B1: Location library
B2: Four candidate sites. Edit any blue cell; column H feeds the model.
B3: ="Model running: "&Inputs!$D$23 -> Model running: Prahladnagar | Rent | Toll roasting | Specialty mix | Base case
B5: Parameter | C5: Units | D5: Prahladnagar | E5: Sindhu Bhavan Road | F5: GIFT City | G5: Sanand | H5: =INDEX(D5:G5,Inputs!$D$15) -> Prahladnagar | J5: Notes & evidence
B6: Café carpet area | C6: sqft | D6: 1000 | E6: 1200 | F6: 900 | G6: 1000 | H6: =INDEX(D6:G6,Inputs!$D$15) -> 1000 | J6: Ground-floor, street-facing unit; 36-52 seats
B7: Seats | C7: # | D7: 40 | E7: 52 | F7: 36 | G7: 40 | H7: =INDEX(D7:G7,Inputs!$D$15) -> 40 | J7: ~22-25 sqft per seat incl. counter & kitchen
B8: Rent | C8: ₹/sqft/mth | D8: 115 | E8: 175 | F8: 110 | G8: 50 | H8: =INDEX(D8:G8,Inputs!$D$15) -> 115 | J8: Listings Oct 2026: Prahladnagar ₹55-120, SBR ₹85-220 (F&B frontage at top end), GIFT ~₹110, Sanand est.
B9: CAM / maintenance | C9: ₹/sqft/mth | D9: 4 | E9: 5 | F9: 15 | G9: 2 | H9: =INDEX(D9:G9,Inputs!$D$15) -> 4 | J9: Grade-A towers in GIFT charge high CAM
B10: Security deposit | C10: months | D10: 4 | E10: 6 | F10: 6 | G10: 3 | H10: =INDEX(D10:G10,Inputs!$D$15) -> 4 | J10: Refundable; 2-6 months typical
B11: Interiors, civil & MEP | C11: ₹/sqft | D11: 2600 | E11: 3000 | F11: 2600 | G11: 2000 | H11: =INDEX(D11:G11,Inputs!$D$15) -> 2600 | J11: Incl. design fees; excludes equipment
B12: Purchase price (own case) | C12: ₹/sqft | D12: 17500 | E12: 24000 | F12: 14000 | G12: 6500 | H12: =INDEX(D12:G12,Inputs!$D$15) -> 17500 | J12: Ground-floor retail, carpet basis; SBR showrooms listed ₹19.5-21.5k on built-up area
B13: Steady-state bills per day | C13: # | D13: 140 | E13: 170 | F13: 150 | G13: 110 | H13: =INDEX(D13:G13,Inputs!$D$15) -> 140 | J13: Year-3 demand at 100% ramp (Base footfall factor 1.0)
B14: Average bill value (ex-GST, FY28) | C14: ₹ | D14: 320 | E14: 360 | F14: 330 | G14: 260 | H14: =INDEX(D14:G14,Inputs!$D$15) -> 320 | J14: Specialty cafés ₹500-1,500 for two in Ahmedabad listings
B15: Operating days per year | C15: days | D15: 360 | E15: 360 | F15: 290 | G15: 350 | H15: =INDEX(D15:G15,Inputs!$D$15) -> 360 | J15: GIFT City: weekday-heavy demand
B16: Delivery share of café revenue | C16: % | D16: 0.15 | E16: 0.1 | F16: 0.06 | G16: 0.15 | H16: =INDEX(D16:G16,Inputs!$D$15) -> 0.15 | J16: Swiggy/Zomato orders
B17: Extra volume growth, Y2-Y6 | C17: % p.a. | D17: 0 | E17: 0.005 | F17: 0.04 | G17: 0.05 | H17: =INDEX(D17:G17,Inputs!$D$15) -> 0 | J17: GIFT workforce & Sanand semiconductor jobs growth
... B19: Wholesale potential factor | C19: x | D19: 1 | E19: 1 | F19: 1.2 | G19: 1.3 | H19: =INDEX(D19:G19,Inputs!$D$15) -> 1 | J19: Office pantries (GIFT), industrial canteens (Sanand)
B20: Property tax & society charges (own) | C20: ₹/sqft/yr | D20: 35 | E20: 40 | F20: 30 | G20: 15 | H20: =INDEX(D20:G20,Inputs!$D$15) -> 35
B21: Property appreciation (own) | C21: % p.a. | D21: 0.05 | E21: 0.06 | F21: 0.07 | G21: 0.06 | H21: =INDEX(D21:G21,Inputs!$D$15) -> 0.05
B23: Derived indicators (Base footfall, Specialty mix, rented)
B24: Rent per seat per month | C24: ₹ | D24: =D6*D8/D7 -> 2875 | E24: =E6*E8/E7 -> 4038.4615 | F24: =F6*F8/F7 -> 2750 | G24: =G6*G8/G7 -> 1250 | H24: =H6*H8/H7 -> 2875
B25: Café revenue at steady state (FY28 prices) | C25: ₹ lakh/yr | D25: =D13*D14*D15/Lakh -> 161.28 | E25: =E13*E14*E15/Lakh -> 220.32 | F25: =F13*F14*F15/Lakh -> 143.55 | G25: =G13*G14*G15/Lakh -> 100.1 | H25: =H13*H14*H15/Lakh -> 161.28
B26: Rent as % of steady-state revenue | C26: % | D26: =D6*D8*12/(D13*D14*D15) -> 0.085565476 | E26: =E6*E8*12/(E13*E14*E15) -> 0.11437908 | F26: =F6*F8*12/(F13*F14*F15) -> 0.082758621 | G26: =G6*G8*12/(G13*G14*G15) -> 0.05994006 | H26: =H6*H8*12/(H13*H14*H15) -> 0.085565476
B27: Interiors cost | C27: ₹ lakh | D27: =D6*D11/Lakh -> 26 | E27: =E6*E11/Lakh -> 36 | F27: =F6*F11/Lakh -> 23.4 | G27: =G6*G11/Lakh -> 20 | H27: =H6*H11/Lakh -> 26
B28: Purchase cost of the unit (own case) | C28: ₹ lakh | D28: =D6*D12/Lakh -> 175 | E28: =E6*E12/Lakh -> 288 | F28: =F6*F12/Lakh -> 126 | G28: =G6*G12/Lakh -> 65 | H28: =H6*H12/Lakh -> 175
B29: Gross rental yield on purchase price | C29: % | D29: =D8*12/D12 -> 0.078857143 | E29: =E8*12/E12 -> 0.0875 | F29: =F8*12/F12 -> 0.094285714 | G29: =G8*12/G12 -> 0.092307692 | H29: =H8*12/H12 -> 0.078857143
B31: Site profiles
B32: Prahladnagar | C32: Corporate Road / 100 ft road office & upscale-residential belt. Dense chain competition (Starbucks, Third Wave, Slay, The Dark Roast).
B33: Sindhu Bhavan Road | C33: Ahmedabad's premier F&B high street (Bodakdev). Highest footfall and spend, evening/weekend peaks, highest rents.
B34: GIFT City | C34: India's IFSC: captive, fast-growing white-collar workforce (>12k, target 1 lakh jobs by 2030), few quality cafés, weekday demand.
B35: Sanand | C35: Industrial boom town: Micron ATMP (opened Feb 2026), Tata EV plants; ~50k semicon jobs planned in Gujarat. Cheap space, low ATV, first-mover play.

Sheet Sourcing
B1: Coffee sourcing & roasting economics
B2: Green prices in ₹/kg (Oct 2026). Mix shares must add to 100%. Column J = active mix.
B3: ="Model running: "&Inputs!$D$23 -> Model running: Prahladnagar | Rent | Toll roasting | Specialty mix | Base case
B5: Roasting & packing parameters
B6: Roast loss (moisture & chaff) | C6: % | D6: 0.16 | F6: 1 kg green -> 0.84 kg roasted
B7: Toll-roasting fee | C7: ₹/kg roasted | D7: 180 | F7: Contract roaster roasts your green
B8: Inbound freight, green or roasted | C8: ₹/kg | D8: 25 | F8: Chikmagalur/Coorg to Ahmedabad
B9: In-house roasting variable cost (LPG, power, bags) | C9: ₹/kg roasted | D9: 35 | F9: Roaster labour & AMC are in fixed costs
B10: Café bulk packing | C10: ₹/kg | D10: 10
B11: Retail bag, valve & label | C11: ₹/kg | D11: 48 | F11: ₹12 per 250 g bag
B12: Wholesale packing | C12: ₹/kg | D12: 45
B14: Green coffee type | C14: Units | D14: Green ₹/kg | E14: Roasted, bought ₹/kg | F14: Value | G14: Specialty | H14: Premium | I14: Custom | J14: =INDEX(F14:I14,Inputs!$D$18) -> Specialty
B15: Commodity arabica (Plantation A) | C15: share | D15: 600 | E15: 1050 | F15: 0.5 | G15: 0 | H15: 0 | I15: 0 | J15: =INDEX(F15:I15,Inputs!$D$18) -> 0
B16: Commodity robusta | C16: share | D16: 440 | E16: 900 | F16: 0.5 | G16: 0 | H16: 0 | I16: 0 | J16: =INDEX(F16:I16,Inputs!$D$18) -> 0
B17: Fine robusta (washed) | C17: share | D17: 520 | E17: 1150 | F17: 0 | G17: 0.2 | H17: 0.1 | I17: 0.15 | J17: =INDEX(F17:I17,Inputs!$D$18) -> 0.2
B18: Estate specialty arabica (83-85) | C18: share | D18: 950 | E18: 1700 | F18: 0 | G18: 0.75 | H18: 0.5 | I18: 0.7 | J18: =INDEX(F18:I18,Inputs!$D$18) -> 0.75
B19: Micro-lot (86+) | C19: share | D19: 2200 | E19: 3200 | F19: 0 | G19: 0.05 | H19: 0.4 | I19: 0.15 | J19: =INDEX(F19:I19,Inputs!$D$18) -> 0.05
B20: Share total (must be 100%) | C20: % | F20: =SUM(F15:F19) -> 1 | G20: =SUM(G15:G19) -> 1 | H20: =SUM(H15:H19) -> 1 | I20: =SUM(I15:I19) -> 1 | J20: =INDEX(F20:I20,Inputs!$D$18) -> 1
B21: Blended green price | C21: ₹/kg | F21: =SUMPRODUCT($D$15:$D$19,F15:F19) -> 520 | G21: =SUMPRODUCT($D$15:$D$19,G15:G19) -> 926.5 | H21: =SUMPRODUCT($D$15:$D$19,H15:H19) -> 1407 | I21: =SUMPRODUCT($D$15:$D$19,I15:I19) -> 1073 | J21: =INDEX(F21:I21,Inputs!$D$18) -> 926.5
B22: Blended roasted price if bought | C22: ₹/kg | F22: =SUMPRODUCT($E$15:$E$19,F15:F19) -> 975 | G22: =SUMPRODUCT($E$15:$E$19,G15:G19) -> 1665 | H22: =SUMPRODUCT($E$15:$E$19,H15:H19) -> 2245 | I22: =SUMPRODUCT($E$15:$E$19,I15:I19) -> 1842.5 | J22: =INDEX(F22:I22,Inputs!$D$18) -> 1665
B23: Green coffee in 1 kg roasted | C23: ₹/kg roasted | F23: =F21/(1-$D$6) -> 619.04762 | G23: =G21/(1-$D$6) -> 1102.9762 | H23: =H21/(1-$D$6) -> 1675 | I23: =I21/(1-$D$6) -> 1277.381 | J23: =INDEX(F23:I23,Inputs!$D$18) -> 1102.9762
B25: Cost per kg of roasted coffee, by route (FY28, before green-price index)
B26: Roaster's margin & conversion (buy roasted) | C26: ₹/kg | F26: =F22-F23 -> 355.95238 | G26: =G22-G23 -> 562.02381 | H26: =H22-H23 -> 570 | I26: =I22-I23 -> 565.11905 | J26: =INDEX(F26:I26,Inputs!$D$18) -> 562.02381
B27: Toll fee + freight (toll roasting) | C27: ₹/kg | F27: =$D$7+$D$8 -> 205 | G27: =$D$7+$D$8 -> 205 | H27: =$D$7+$D$8 -> 205 | I27: =$D$7+$D$8 -> 205 | J27: =INDEX(F27:I27,Inputs!$D$18) -> 205
B28: Variable roasting cost + freight (in-house) | C28: ₹/kg | F28: =$D$9+$D$8 -> 60 | G28: =$D$9+$D$8 -> 60 | H28: =$D$9+$D$8 -> 60 | I28: =$D$9+$D$8 -> 60 | J28: =INDEX(F28:I28,Inputs!$D$18) -> 60
B29: Total: Buy roasted | C29: ₹/kg | F29: =F23+F26 -> 975 | G29: =G23+G26 -> 1665 | H29: =H23+H26 -> 2245 | I29: =I23+I26 -> 1842.5 | J29: =INDEX(F29:I29,Inputs!$D$18) -> 1665
B30: Total: Toll roasting | C30: ₹/kg | F30: =F23+F27 -> 824.04762 | G30: =G23+G27 -> 1307.9762 | H30: =H23+H27 -> 1880 | I30: =I23+I27 -> 1482.381 | J30: =INDEX(F30:I30,Inputs!$D$18) -> 1307.9762
B31: Total: In-house roastery (variable only) | C31: ₹/kg | F31: =F23+F28 -> 679.04762 | G31: =G23+G28 -> 1162.9762 | H31: =H23+H28 -> 1735 | I31: =I23+I28 -> 1337.381 | J31: =INDEX(F31:I31,Inputs!$D$18) -> 1162.9762
B32: Coffee cost per 18 g double shot, toll route | C32: ₹ | F32: =F30*18/1000 -> 14.832857 | G32: =G30*18/1000 -> 23.543571 | H32: =H30*18/1000 -> 33.84 | I32: =I30*18/1000 -> 26.682857 | J32: =INDEX(F32:I32,Inputs!$D$18) -> 23.543571
B34: Demand & price effects of the bean mix
B35: Average-bill premium vs Specialty | C35: % | F35: -0.1 | G35: 0 | H35: 0.05 | I35: 0.02 | J35: =INDEX(F35:I35,Inputs!$D$18) -> 0 | L35: Menu pricing the bean quality supports
B36: Footfall effect vs Specialty | C36: % | F36: 0.05 | G36: 0 | H36: -0.05 | I36: 0 | J36: =INDEX(F36:I36,Inputs!$D$18) -> 0 | L36: Value draws a broader crowd; Premium narrows it
B37: Retail bean price (own label) | C37: ₹/kg | F37: 1600 | G37: 2400 | H37: 3600 | I37: 2800 | J37: =INDEX(F37:I37,Inputs!$D$18) -> 2400 | L37: ₹400 / ₹600 / ₹900 / ₹700 per 250 g bag
B38: Wholesale roasted-bean price (FY28) | C38: ₹/kg | F38: 900 | G38: 1450 | H38: 2300 | I38: 1700 | J38: =INDEX(F38:I38,Inputs!$D$18) -> 1450 | L38: To offices, cafés & hotels (in-house roastery only)
B40: Roasting routes (drop-down list)
B41: Route options | F41: Buy roasted | G41: Toll roasting | H41: In-house roastery
B43: Active coffee cost (feeds the Model)
B44: Green coffee per kg roasted, active mix | C44: ₹/kg | J44: =$J$23 -> 1102.9762
B45: Conversion cost per kg, active route | C45: ₹/kg | J45: =CHOOSE(Inputs!$D$17,$J$26,$J$27,$J$28) -> 205
B46: Roasted coffee cost per kg (FY28 basis) | C46: ₹/kg | J46: =$J$44+$J$45 -> 1307.9762
B47: Own-label retail price | C47: ₹/kg | J47: =$J$37 -> 2400
B48: Wholesale price, active mix | C48: ₹/kg | J48: =$J$38 -> 1450
B49: Average-bill premium of active mix | C49: % | J49: =$J$35 -> 0
B50: Footfall effect of active mix | C50: % | J50: =$J$36 -> 0

Sheet Capex
B1: Capex, property & funding
B2: Unit costs in ₹ (ex-GST, Oct 2026). Amounts in ₹ lakh include the scenario capex-overrun and any Scenarios-sheet capex multiplier.
B3: ="Model running: "&Inputs!$D$23 -> Model running: Prahladnagar | Rent | Toll roasting | Specialty mix | Base case
B5: Equipment & fit-out
B6: Item | C6: Basis | D6: Unit cost ₹ | E6: Quantity | F6: Asset class | G6: ₹ lakh | I6: Notes
B7: Interiors, civil, MEP & design | C7: per sqft (site) | D7: =Locations!$H$11 -> 2600 | E7: =Locations!$H$6 -> 1000 | F7: Interiors | G7: =D7*E7*(1+Inputs!$D$56)*Scenarios!$D$40/Lakh -> 27.3 | I7: Site-specific rate from Locations
B8: HVAC (ductable / split ACs) | C8: per sqft | D8: 450 | E8: =Locations!$H$6 -> 1000 | F8: Equipment | G8: =D8*E8*(1+Inputs!$D$56)*Scenarios!$D$40/Lakh -> 4.725
B9: Electrical upgrade, UPS & DG share | C9: lump sum | D9: 250000 | E9: =1 -> 1 | F9: Equipment | G9: =D9*E9*(1+Inputs!$D$56)*Scenarios!$D$40/Lakh -> 2.625
B10: Espresso machine, 2-group multi-boiler | C10: lump sum | D10: 800000 | E10: =1 -> 1 | F10: Equipment | G10: =D10*E10*(1+Inputs!$D$56)*Scenarios!$D$40/Lakh -> 8.4 | I10: La Marzocco Linea PB 2GR ₹11.26 lakh + GST; Brewlyn 2GR ₹6.30 lakh
B11: Grinders: 2 on-demand espresso + 1 filter | C11: lump sum | D11: 420000 | E11: =1 -> 1 | F11: Equipment | G11: =D11*E11*(1+Inputs!$D$56)*Scenarios!$D$40/Lakh -> 4.41
B12: Brew bar, cold-brew kit & water boiler | C12: lump sum | D12: 150000 | E12: =1 -> 1 | F12: Equipment | G12: =D12*E12*(1+Inputs!$D$56)*Scenarios!$D$40/Lakh -> 1.575
B13: Kitchen equipment & refrigeration | C13: lump sum | D13: 550000 | E13: =1 -> 1 | F13: Equipment | G13: =D13*E13*(1+Inputs!$D$56)*Scenarios!$D$40/Lakh -> 5.775
B14: Water treatment (RO + softener + remineralisation) | C14: lump sum | D14: 100000 | E14: =1 -> 1 | F14: Equipment | G14: =D14*E14*(1+Inputs!$D$56)*Scenarios!$D$40/Lakh -> 1.05
B15: Furniture & seating | C15: per seat | D15: 12000 | E15: =Locations!$H$7 -> 40 | F15: Furniture | G15: =D15*E15*(1+Inputs!$D$56)*Scenarios!$D$40/Lakh -> 5.04
B16: Crockery, glassware & smallwares | C16: lump sum | D16: 150000 | E16: =1 -> 1 | F16: Furniture | G16: =D16*E16*(1+Inputs!$D$56)*Scenarios!$D$40/Lakh -> 1.575
B17: Signage & branding | C17: lump sum | D17: 200000 | E17: =1 -> 1 | F17: Furniture | G17: =D17*E17*(1+Inputs!$D$56)*Scenarios!$D$40/Lakh -> 2.1
B18: POS, CCTV, audio & Wi-Fi | C18: lump sum | D18: 180000 | E18: =1 -> 1 | F18: IT | G18: =D18*E18*(1+Inputs!$D$56)*Scenarios!$D$40/Lakh -> 1.89
B19: 3 kg drum roaster (Indian-made) incl. install | C19: in-house only | D19: 900000 | E19: =Inputs!$D$21 -> 0 | F19: Roastery | G19: =D19*E19*(1+Inputs!$D$56)*Scenarios!$D$40/Lakh -> 0 | I19: Aaroasta (Rajkot) ARST-3, LPG, 6-9 kg/hour
B20: Afterburner, chimney & ducting | C20: in-house only | D20: 250000 | E20: =Inputs!$D$21 -> 0 | F20: Roastery | G20: =D20*E20*(1+Inputs!$D$56)*Scenarios!$D$40/Lakh -> 0
B21: QC & packing kit (moisture meter, sealer, sample roaster) | C21: in-house only | D21: 150000 | E21: =Inputs!$D$21 -> 0 | F21: Roastery | G21: =D21*E21*(1+Inputs!$D$56)*Scenarios!$D$40/Lakh -> 0
B22: Roastery area fit-out (150 sqft) | C22: roastery sqft | D22: =Locations!$H$11 -> 2600 | E22: =Inputs!$D$21*Inputs!$D$113 -> 0 | F22: Interiors | G22: =D22*E22*(1+Inputs!$D$56)*Scenarios!$D$40/Lakh -> 0
B23: Café & roastery capex | G23: =SUM(G7:G22) -> 66.465
B25: Premises (own case)
B26: Area occupied (café + roastery if in-house) | C26: sqft | G26: =Locations!$H$6+Inputs!$D$21*Inputs!$D$113 -> 1000
B27: Purchase price, active location | C27: ₹/sqft | G27: =Locations!$H$12 -> 17500
B28: Purchase price | C28: ₹ lakh | G28: =Inputs!$D$20*$G$26*$G$27/Lakh -> 0
B29: Stamp duty & registration | C29: ₹ lakh | G29: =$G$28*Inputs!$D$127 -> 0
B30: Legal & brokerage | C30: ₹ lakh | G30: =$G$28*Inputs!$D$128 -> 0
B31: Total property cost | C31: ₹ lakh | G31: =$G$28+$G$29+$G$30 -> 0
B32: of which land (not depreciated) | C32: ₹ lakh | G32: =$G$31*Inputs!$D$129 -> 0
B33: of which building | C33: ₹ lakh | G33: =$G$31-$G$32 -> 0
B35: Initial capex by asset class
B36: Asset class | D36: ₹ lakh | E36: Book life | F36: Tax WDV rate
B37: Interiors | D37: =SUMIF($F$7:$F$22,"Interiors",$G$7:$G$22) -> 27.3 | E37: 9 | F37: 0.1
B38: Equipment | D38: =SUMIF($F$7:$F$22,"Equipment",$G$7:$G$22) -> 28.56 | E38: 8 | F38: 0.15
B39: Furniture | D39: =SUMIF($F$7:$F$22,"Furniture",$G$7:$G$22) -> 8.715 | E39: 8 | F39: 0.1
B40: IT | D40: =SUMIF($F$7:$F$22,"IT",$G$7:$G$22) -> 1.89 | E40: 4 | F40: 0.4
B41: Roastery | D41: =SUMIF($F$7:$F$22,"Roastery",$G$7:$G$22) -> 0 | E41: 10 | F41: 0.15
B42: Building | D42: =$G$33 -> 0 | E42: 60 | F42: 0.1
B43: Land | D43: =$G$32 -> 0 | E43: 0 | F43: 0
B44: Total initial capex incl. property | D44: =SUM($D$37:$D$43) -> 66.465
B45: Book: straight line from Y1 (land not depreciated). Tax: Income-tax Act block rates, WDV; furniture & fittings 10%, plant & machinery 15%, computers 40%, buildings 10%.
B47: Sources & uses of funds (Y0)
B48: Café & roastery capex | C48: ₹ lakh | G48: =$G$23 -> 66.465
B49: Property purchase incl. stamp duty | C49: ₹ lakh | G49: =$G$31 -> 0
B50: Pre-opening expenses | C50: ₹ lakh | G50: =Model!F135 -> 11.0545
B51: Rent deposit (refundable) | C51: ₹ lakh | G51: =(1-Inputs!$D$20)*Locations!$H$10*$G$26*Locations!$H$8*Scenarios!$D$38/Lakh -> 4.6
B52: Opening cash: minimum balance + ramp-up reserve | C52: ₹ lakh | G52: =Inputs!$D$149/Lakh+Inputs!$D$150*Model!G137/12 -> 19.1085
B53: Total capital requirement | C53: ₹ lakh | G53: =$G$48+$G$49+$G$50+$G$51+$G$52 -> 101.228
B55: Loan share, active premises | C55: % | G55: =IF(Inputs!$D$20=1,Inputs!$D$143,Inputs!$D$142) -> 0.5
B56: Term loan | C56: ₹ lakh | G56: =IF($G$53*Lakh<=Inputs!$D$141,0,ROUND($G$55*($G$48+$G$49),1)) -> 33.2 | I56: All-equity if the requirement is within ₹15 lakh, else loan on capex/property
B57: Promoter equity | C57: ₹ lakh | G57: =$G$53-$G$56 -> 68.028
B58: Total sources | C58: ₹ lakh | G58: =$G$56+$G$57 -> 101.228
B59: Debt / total capital | C59: % | G59: =$G$56/$G$58 -> 0.3279725
B60: Loan interest rate | C60: % | G60: =IF(Inputs!$D$20=1,Inputs!$D$145,Inputs!$D$144) -> 0.11
B61: Loan tenor | C61: years | G61: =IF(Inputs!$D$20=1,Inputs!$D$147,Inputs!$D$146) -> 5

Sheet Model
B1: Model: three statements & schedules
B2: ₹ lakh unless stated. Statements contain links only; all workings are in the schedules below.
B3: ="Model running: "&Inputs!$D$23 -> Model running: Prahladnagar | Rent | Toll roasting | Specialty mix | Base case
B5: ₹ lakh unless stated | C5: Units | D5: Value | F5: =Inputs!F5 -> 2027 | G5: =Inputs!G5 -> 2028 | H5: =Inputs!H5 -> 2029 | I5: =Inputs!I5 -> 2030 | J5: =Inputs!J5 -> 2031 | K5: =Inputs!K5 -> 2032 | L5: =Inputs!L5 -> 2033 | M5: =Inputs!M5 -> 2034 | ... P5: =Inputs!P5 -> 2037
B6: Period (Y0 = pre-opening fit-out year) | F6: =F5-Inputs!$D$26 -> 0 | G6: =G5-Inputs!$D$26 -> 1 | H6: =H5-Inputs!$D$26 -> 2 | I6: =I5-Inputs!$D$26 -> 3 | J6: =J5-Inputs!$D$26 -> 4 | K6: =K5-Inputs!$D$26 -> 5 | L6: =L5-Inputs!$D$26 -> 6 | M6: =M5-Inputs!$D$26 -> 7 | ... P6: =P5-Inputs!$D$26 -> 10
B7: Operating flag | C7: 1/0 | F7: =IF(F6>=1,1,0) -> 0 | G7: =IF(G6>=1,1,0) -> 1 | H7: =IF(H6>=1,1,0) -> 1 | I7: =IF(I6>=1,1,0) -> 1 | J7: =IF(J6>=1,1,0) -> 1 | K7: =IF(K6>=1,1,0) -> 1 | L7: =IF(L6>=1,1,0) -> 1 | M7: =IF(M6>=1,1,0) -> 1 | ... P7: =IF(P6>=1,1,0) -> 1
B8: Food & supplies price index | C8: x | F8: =(1+Inputs!$D$73)^MAX(0,F6-1) -> 1 | G8: =(1+Inputs!$D$73)^MAX(0,G6-1) -> 1 | H8: =(1+Inputs!$D$73)^MAX(0,H6-1) -> 1.05 | I8: =(1+Inputs!$D$73)^MAX(0,I6-1) -> 1.1025 | J8: =(1+Inputs!$D$73)^MAX(0,J6-1) -> 1.157625 | K8: =(1+Inputs!$D$73)^MAX(0,K6-1) -> 1.2155063 | L8: =(1+Inputs!$D$73)^MAX(0,L6-1) -> 1.2762816 | M8: =(1+Inputs!$D$73)^MAX(0,M6-1) -> 1.3400956 | ... P8: =(1+Inputs!$D$73)^MAX(0,P6-1) -> 1.5513282
B9: General cost index | C9: x | F9: =(1+Inputs!$D$111)^MAX(0,F6-1) -> 1 | G9: =(1+Inputs!$D$111)^MAX(0,G6-1) -> 1 | H9: =(1+Inputs!$D$111)^MAX(0,H6-1) -> 1.05 | I9: =(1+Inputs!$D$111)^MAX(0,I6-1) -> 1.1025 | J9: =(1+Inputs!$D$111)^MAX(0,J6-1) -> 1.157625 | K9: =(1+Inputs!$D$111)^MAX(0,K6-1) -> 1.2155063 | L9: =(1+Inputs!$D$111)^MAX(0,L6-1) -> 1.2762816 | M9: =(1+Inputs!$D$111)^MAX(0,M6-1) -> 1.3400956 | ... P9: =(1+Inputs!$D$111)^MAX(0,P6-1) -> 1.5513282
B11: Income statement
B12: Beverages | C12: ₹ lakh | F12: =F92 -> 0 | G12: =G92 -> 64.99584 | H12: =H92 -> 89.244288 | I12: =I92 -> 110.24294 | J12: =J92 -> 118.64897 | K12: =K92 -> 127.69595 | L12: =L92 -> 137.43277 | M12: =M92 -> 147.91202 | ... P12: =P92 -> 184.39237
B13: Food | C13: ₹ lakh | F13: =F93 -> 0 | G13: =G93 -> 31.4496 | H13: =H93 -> 43.18272 | I13: =I93 -> 53.34336 | J13: =J93 -> 57.410791 | K13: =K93 -> 61.788364 | L13: =L93 -> 66.499727 | M13: =M93 -> 71.570331 | ... P13: =P93 -> 89.222116
B14: Retail beans & merchandise | C14: ₹ lakh | F14: =F94 -> 0 | G14: =G94 -> 8.38656 | H14: =H94 -> 11.515392 | I14: =I94 -> 14.224896 | J14: =J94 -> 15.309544 | K14: =K94 -> 16.476897 | L14: =L94 -> 17.73326 | M14: =M94 -> 19.085422 | ... P14: =P94 -> 23.792564
B15: Wholesale roasted beans | C15: ₹ lakh | F15: =F97 -> 0 | G15: =G97 -> 0 | H15: =H97 -> 0 | I15: =I97 -> 0 | J15: =J97 -> 0 | K15: =K97 -> 0 | L15: =L97 -> 0 | M15: =M97 -> 0 | ... P15: =P97 -> 0
B16: Revenue | C16: ₹ lakh | F16: =SUM(F12:F15) -> 0 | G16: =SUM(G12:G15) -> 104.832 | H16: =SUM(H12:H15) -> 143.9424 | I16: =SUM(I12:I15) -> 177.8112 | J16: =SUM(J12:J15) -> 191.3693 | K16: =SUM(K12:K15) -> 205.96121 | L16: =SUM(L12:L15) -> 221.66576 | M16: =SUM(M12:M15) -> 238.56777 | ... P16: =SUM(P12:P15) -> 297.40705
B17: growth | C17: % | H17: =IF(G16>0,H16/G16-1,0) -> 0.37307692 | I17: =IF(H16>0,I16/H16-1,0) -> 0.23529412 | J17: =IF(I16>0,J16/I16-1,0) -> 0.07625 | K17: =IF(J16>0,K16/J16-1,0) -> 0.07625 | L17: =IF(K16>0,L16/K16-1,0) -> 0.07625 | M17: =IF(L16>0,M16/L16-1,0) -> 0.07625 | N17: =IF(M16>0,N16/M16-1,0) -> 0.07625 | O17: =IF(N16>0,O16/N16-1,0) -> 0.07625 | P17: =IF(O16>0,P16/O16-1,0) -> 0.07625
B18: Cost of goods sold | C18: ₹ lakh | F18: =-F114 -> 0 | G18: =-G114 -> -31.702697 | H18: =-H114 -> -43.299044 | I18: =-I114 -> -53.206899 | J18: =-J114 -> -56.967774 | K18: =-K114 -> -60.999582 | L18: =-L114 -> -65.321642 | M18: =-M114 -> -69.954672 | ... P18: =-P114 -> -85.954798
B19: Gross profit | C19: ₹ lakh | F19: =F16+F18 -> 0 | G19: =G16+G18 -> 73.129303 | H19: =H16+H18 -> 100.64336 | I19: =I16+I18 -> 124.6043 | J19: =J16+J18 -> 134.40153 | K19: =K16+K18 -> 144.96163 | L19: =L16+L18 -> 156.34411 | M19: =M16+M18 -> 168.6131 | ... P19: =P16+P18 -> 211.45226
B20: gross margin | C20: % | F20: =IF(F16>0,F19/F16,0) -> 0 | G20: =IF(G16>0,G19/G16,0) -> 0.69758569 | H20: =IF(H16>0,H19/H16,0) -> 0.69919187 | I20: =IF(I16>0,I19/I16,0) -> 0.70076745 | J20: =IF(J16>0,J19/J16,0) -> 0.70231499 | K20: =IF(K16>0,K19/K16,0) -> 0.70382976 | L20: =IF(L16>0,L19/L16,0) -> 0.70531469 | M20: =IF(M16>0,M19/M16,0) -> 0.70677233 | ... P20: =IF(P16>0,P19/P16,0) -> 0.71098601
B21: Staff costs | C21: ₹ lakh | F21: =-F121 -> 0 | G21: =-G121 -> -39.054 | H21: =-H121 -> -42.17832 | I21: =-I121 -> -45.552586 | J21: =-J121 -> -49.811752 | K21: =-K121 -> -54.477453 | L21: =-L121 -> -59.589251 | M21: =-M121 -> -65.190629 | ... P21: =-P121 -> -85.434393
B22: Rent, CAM & property tax | C22: ₹ lakh | F22: =-(F122+F123+F124) -> 0 | G22: =-(G122+G123+G124) -> -14.28 | H22: =-(H122+H123+H124) -> -14.994 | I22: =-(I122+I123+I124) -> -15.7437 | J22: =-(J122+J123+J124) -> -16.530885 | K22: =-(K122+K123+K124) -> -17.357429 | L22: =-(L122+L123+L124) -> -18.225301 | M22: =-(M122+M123+M124) -> -19.136566 | ... P22: =-(P122+P123+P124) -> -22.152967
B23: Electricity, gas & water | C23: ₹ lakh | F23: =-(F125+F126) -> 0 | G23: =-(G125+G126) -> -7.5 | H23: =-(H125+H126) -> -7.818 | I23: =-(I125+I126) -> -8.14962 | J23: =-(J125+J126) -> -8.4954498 | K23: =-(K125+K126) -> -8.856105 | L23: =-(L125+L126) -> -9.2322284 | M23: =-(M125+M126) -> -9.6244906 | ... P23: =-(P125+P126) -> -10.905268
B24: Marketing | C24: ₹ lakh | F24: =-F127 -> 0 | G24: =-G127 -> -5.2416 | H24: =-H127 -> -4.318272 | I24: =-I127 -> -5.334336 | J24: =-J127 -> -5.7410791 | K24: =-K127 -> -6.1788364 | L24: =-L127 -> -6.6499727 | M24: =-M127 -> -7.1570331 | ... P24: =-P127 -> -8.9222116
B25: Aggregator & payment fees | C25: ₹ lakh | F25: =-(F130+F131) -> 0 | G25: =-(G130+G131) -> -4.5549504 | H25: =-(H130+H131) -> -6.2542973 | I25: =-(I130+I131) -> -7.7258966 | J25: =-(J130+J131) -> -8.3149963 | K25: =-(K130+K131) -> -8.9490147 | L25: =-(L130+L131) -> -9.6313771 | M25: =-(M130+M131) -> -10.36577 | ... P25: =-(P130+P131) -> -12.922336
B26: Repairs, maintenance & AMC | C26: ₹ lakh | F26: =-(F128+F129) -> 0 | G26: =-(G128+G129) -> -2.17248 | H26: =-(H128+H129) -> -2.789136 | I26: =-(I128+I129) -> -3.328668 | J26: =-(J128+J129) -> -3.5651146 | K26: =-(K128+K129) -> -3.818722 | L26: =-(L128+L129) -> -4.0907553 | M26: =-(M128+M129) -> -4.3825739 | ... P26: =-(P128+P129) -> -5.3919027
B27: Admin, wholesale selling & other | C27: ₹ lakh | F27: =-(F132+F133+F134) -> 0 | G27: =-(G132+G133+G134) -> -4.04832 | H27: =-(H132+H133+H134) -> -4.589424 | I27: =-(I132+I133+I134) -> -5.085612 | J27: =-(J132+J133+J134) -> -5.386568 | K27: =-(K132+K133+K134) -> -5.7061309 | L27: =-(L132+L133+L134) -> -6.0455022 | M27: =-(M132+M133+M134) -> -6.4059646 | ... P27: =-(P132+P133+P134) -> -7.6280552
B28: Pre-opening expenses | C28: ₹ lakh | F28: =-F135 -> -11.0545 | G28: =-G135 -> 0 | H28: =-H135 -> 0 | I28: =-I135 -> 0 | J28: =-J135 -> 0 | K28: =-K135 -> 0 | L28: =-L135 -> 0 | M28: =-M135 -> 0 | ... P28: =-P135 -> 0
B29: EBITDA | C29: ₹ lakh | F29: =SUM(F19,F21:F28) -> -11.0545 | G29: =SUM(G19,G21:G28) -> -3.722047 | H29: =SUM(H19,H21:H28) -> 17.701906 | I29: =SUM(I19,I21:I28) -> 33.683883 | J29: =SUM(J19,J21:J28) -> 36.555685 | K29: =SUM(K19,K21:K28) -> 39.61794 | L29: =SUM(L19,L21:L28) -> 42.879726 | M29: =SUM(M19,M21:M28) -> 46.350071 | ... P29: =SUM(P19,P21:P28) -> 58.095121
B30: EBITDA margin | C30: % | F30: =IF(F16>0,F29/F16,0) -> 0 | G30: =IF(G16>0,G29/G16,0) -> -0.035504875 | H30: =IF(H16>0,H29/H16,0) -> 0.1229791 | I30: =IF(I16>0,I29/I16,0) -> 0.18943623 | J30: =IF(J16>0,J29/J16,0) -> 0.19102168 | K30: =IF(K16>0,K29/K16,0) -> 0.19235632 | L30: =IF(L16>0,L29/L16,0) -> 0.19344317 | M30: =IF(M16>0,M29/M16,0) -> 0.19428471 | ... P30: =IF(P16>0,P29/P16,0) -> 0.19533875
B31: Depreciation | C31: ₹ lakh | F31: =-F157 -> 0 | G31: =-G157 -> -8.1652083 | H31: =-H157 -> -8.4797043 | I31: =-I157 -> -8.9115315 | J31: =-J157 -> -9.4449651 | K31: =-K157 -> -9.546573 | L31: =-L157 -> -10.164457 | M31: =-M157 -> -12.813222 | ... P31: =-P157 -> -5.8961331
B32: EBIT | C32: ₹ lakh | F32: =F29+F31 -> -11.0545 | G32: =G29+G31 -> -11.887255 | H32: =H29+H31 -> 9.222202 | I32: =I29+I31 -> 24.772351 | J32: =J29+J31 -> 27.11072 | K32: =K29+K31 -> 30.071367 | L32: =L29+L31 -> 32.71527 | M32: =M29+M31 -> 33.536849 | ... P32: =P29+P31 -> 52.198988
B33: Interest expense | C33: ₹ lakh | F33: =-(F204+F210) -> 0 | G33: =-(G204+G210) -> -3.652 | H33: =-(H204+H210) -> -2.9216 | I33: =-(I204+I210) -> -2.1912 | J33: =-(J204+J210) -> -1.4608 | K33: =-(K204+K210) -> -0.7304 | L33: =-(L204+L210) -> 0 | M33: =-(M204+M210) -> 0 | ... P33: =-(P204+P210) -> 0
B34: Interest income | C34: ₹ lakh | F34: =F211 -> 0 | G34: =G211 -> 0.76434 | H34: =H211 -> 0.12317974 | I34: =I211 -> 0.34997769 | J34: =J211 -> 1.1799754 | K34: =K211 -> 1.944653 | L34: =L211 -> 2.8323472 | M34: =M211 -> 3.6676624 | ... P34: =P211 -> 8.345452
B35: Profit before tax | C35: ₹ lakh | F35: =F32+F33+F34 -> -11.0545 | G35: =G32+G33+G34 -> -14.774915 | H35: =H32+H33+H34 -> 6.4237817 | I35: =I32+I33+I34 -> 22.931129 | J35: =J32+J33+J34 -> 26.829895 | K35: =K32+K33+K34 -> 31.28562 | L35: =L32+L33+L34 -> 35.547617 | M35: =M32+M33+M34 -> 37.204511 | ... P35: =P32+P33+P34 -> 60.54444
B36: Current tax | C36: ₹ lakh | F36: =-F186 -> 0 | G36: =-G186 -> 0 | H36: =-H186 -> 0 | I36: =-I186 -> -1.4185691 | J36: =-J186 -> -7.5145407 | K36: =-K186 -> -8.7685329 | L36: =-L186 -> -9.8613591 | M36: =-M186 -> -10.821242 | ... P36: =-P186 -> -15.192589
B37: Deferred tax | C37: ₹ lakh | F37: =-F174 -> 0 | G37: =-G174 -> -0.14955522 | H37: =-H174 -> 0.19209162 | I37: =-I174 -> 0.488736 | J37: =-J174 -> 0.76199261 | K37: =-K174 -> 0.89456793 | L37: =-L174 -> 0.91473493 | M37: =-M174 -> 1.4576109 | ... P37: =-P174 -> -0.045235453
B38: Profit after tax | C38: ₹ lakh | F38: =F35+F36+F37 -> -11.0545 | G38: =G35+G36+G37 -> -14.924471 | H38: =H35+H36+H37 -> 6.6158733 | I38: =I35+I36+I37 -> 22.001296 | J38: =J35+J36+J37 -> 20.077347 | K38: =K35+K36+K37 -> 23.411655 | L38: =L35+L36+L37 -> 26.600993 | M38: =M35+M36+M37 -> 27.84088 | ... P38: =P35+P36+P37 -> 45.306616
B39: net margin | C39: % | F39: =IF(F16>0,F38/F16,0) -> 0 | G39: =IF(G16>0,G38/G16,0) -> -0.1423656 | H39: =IF(H16>0,H38/H16,0) -> 0.04596195 | I39: =IF(I16>0,I38/I16,0) -> 0.12373403 | J39: =IF(J16>0,J38/J16,0) -> 0.10491415 | K39: =IF(K16>0,K38/K16,0) -> 0.11367022 | L39: =IF(L16>0,L38/L16,0) -> 0.12000497 | M39: =IF(M16>0,M38/M16,0) -> 0.11670009 | ... P39: =IF(P16>0,P38/P16,0) -> 0.15233874
B41: Cash flow statement
B42: Profit after tax | C42: ₹ lakh | F42: =F38 -> -11.0545 | G42: =G38 -> -14.924471 | H42: =H38 -> 6.6158733 | I42: =I38 -> 22.001296 | J42: =J38 -> 20.077347 | K42: =K38 -> 23.411655 | L42: =L38 -> 26.600993 | M42: =M38 -> 27.84088 | ... P42: =P38 -> 45.306616
B43: Add: depreciation | C43: ₹ lakh | F43: =F157 -> 0 | G43: =G157 -> 8.1652083 | H43: =H157 -> 8.4797043 | I43: =I157 -> 8.9115315 | J43: =J157 -> 9.4449651 | K43: =K157 -> 9.546573 | L43: =L157 -> 10.164457 | M43: =M157 -> 12.813222 | ... P43: =P157 -> 5.8961331
B44: Add: deferred tax | C44: ₹ lakh | F44: =F174 -> 0 | G44: =G174 -> 0.14955522 | H44: =H174 -> -0.19209162 | I44: =I174 -> -0.488736 | J44: =J174 -> -0.76199261 | K44: =K174 -> -0.89456793 | L44: =L174 -> -0.91473493 | M44: =M174 -> -1.4576109 | ... P44: =P174 -> 0.045235453
B45: Less: increase in working capital | C45: ₹ lakh | F45: =-F194 -> 0 | G45: =-G194 -> -1.2068196 | H45: =-H194 -> -0.43440114 | I45: =-I194 -> -0.36698081 | J45: =-J194 -> -0.13284104 | K45: =-K194 -> -0.14188566 | L45: =-L194 -> -0.15152823 | M45: =-M194 -> -0.16180917 | ... P45: =-P194 -> -0.1971548
B46: Cash from operations | C46: ₹ lakh | F46: =SUM(F42:F45) -> -11.0545 | G46: =SUM(G42:G45) -> -7.8165266 | H46: =SUM(H42:H45) -> 14.469085 | I46: =SUM(I42:I45) -> 30.057111 | J46: =SUM(J42:J45) -> 28.627479 | K46: =SUM(K42:K45) -> 31.921775 | L46: =SUM(L42:L45) -> 35.699186 | M46: =SUM(M42:M45) -> 39.034682 | ... P46: =SUM(P42:P45) -> 51.050829
B47: Capex incl. property | C47: ₹ lakh | F47: =-F148 -> -66.465 | G47: =-G148 -> -1.57248 | H47: =-H148 -> -2.159136 | I47: =-I148 -> -2.667168 | J47: =-J148 -> -2.8705396 | K47: =-K148 -> -3.0894182 | L47: =-L148 -> -14.816306 | M47: =-M148 -> -3.5785165 | ... P47: =-P148 -> -4.4611058
B48: Rent deposit paid | C48: ₹ lakh | F48: =-F195 -> -4.6 | G48: =-G195 -> 0 | H48: =-H195 -> 0 | I48: =-I195 -> 0 | J48: =-J195 -> 0 | K48: =-K195 -> 0 | L48: =-L195 -> 0 | M48: =-M195 -> 0 | ... P48: =-P195 -> 0
B49: Cash from investing | C49: ₹ lakh | F49: =F47+F48 -> -71.065 | G49: =G47+G48 -> -1.57248 | H49: =H47+H48 -> -2.159136 | I49: =I47+I48 -> -2.667168 | J49: =J47+J48 -> -2.8705396 | K49: =K47+K48 -> -3.0894182 | L49: =L47+L48 -> -14.816306 | M49: =M47+M48 -> -3.5785165 | ... P49: =P47+P48 -> -4.4611058
B50: Term loan drawn | C50: ₹ lakh | F50: =F201 -> 33.2 | G50: =G201 -> 0 | H50: =H201 -> 0 | I50: =I201 -> 0 | J50: =J201 -> 0 | K50: =K201 -> 0 | L50: =L201 -> 0 | M50: =M201 -> 0 | ... P50: =P201 -> 0
B51: Term loan repaid | C51: ₹ lakh | F51: =-F202 -> 0 | G51: =-G202 -> -6.64 | H51: =-H202 -> -6.64 | I51: =-I202 -> -6.64 | J51: =-J202 -> -6.64 | K51: =-K202 -> -6.64 | L51: =-L202 -> 0 | M51: =-M202 -> 0 | ... P51: =-P202 -> 0
B52: Cash credit drawn / (repaid) | C52: ₹ lakh | F52: =F208 -> 0 | G52: =G208 -> 0 | H52: =H208 -> 0 | I52: =I208 -> 0 | J52: =J208 -> 0 | K52: =K208 -> 0 | L52: =L208 -> 0 | M52: =M208 -> 0 | ... P52: =P208 -> 0
B53: Equity invested | C53: ₹ lakh | F53: =F216 -> 68.028 | G53: =G216 -> 0 | H53: =H216 -> 0 | I53: =I216 -> 0 | J53: =J216 -> 0 | K53: =K216 -> 0 | L53: =L216 -> 0 | M53: =M216 -> 0 | ... P53: =P216 -> 0
B54: Dividends paid | C54: ₹ lakh | F54: =-F220 -> 0 | G54: =-G220 -> 0 | H54: =-H220 -> 0 | I54: =-I220 -> 0 | J54: =-J220 -> 0 | K54: =-K220 -> 0 | L54: =-L220 -> 0 | M54: =-M220 -> 0 | ... P54: =-P220 -> 0
B55: Cash from financing | C55: ₹ lakh | F55: =SUM(F50:F54) -> 101.228 | G55: =SUM(G50:G54) -> -6.64 | H55: =SUM(H50:H54) -> -6.64 | I55: =SUM(I50:I54) -> -6.64 | J55: =SUM(J50:J54) -> -6.64 | K55: =SUM(K50:K54) -> -6.64 | L55: =SUM(L50:L54) -> 0 | M55: =SUM(M50:M54) -> 0 | ... P55: =SUM(P50:P54) -> 0
B56: Net change in cash | C56: ₹ lakh | F56: =F46+F49+F55 -> 19.1085 | G56: =G46+G49+G55 -> -16.029007 | H56: =H46+H49+H55 -> 5.6699489 | I56: =I46+I49+I55 -> 20.749943 | J56: =J46+J49+J55 -> 19.116939 | K56: =K46+K49+K55 -> 22.192357 | L56: =L46+L49+L55 -> 20.88288 | M56: =M46+M49+M55 -> 35.456165 | ... P56: =P46+P49+P55 -> 46.589724
B57: Opening cash | C57: ₹ lakh | G57: =F58 -> 19.1085 | H57: =G58 -> 3.0794934 | I57: =H58 -> 8.7494423 | J57: =I58 -> 29.499385 | K57: =J58 -> 48.616324 | L57: =K58 -> 70.808681 | M57: =L58 -> 91.691561 | N57: =M58 -> 127.14773 | ... P57: =O58 -> 208.6363
B58: Closing cash | C58: ₹ lakh | F58: =F57+F56 -> 19.1085 | G58: =G57+G56 -> 3.0794934 | H58: =H57+H56 -> 8.7494423 | I58: =I57+I56 -> 29.499385 | J58: =J57+J56 -> 48.616324 | K58: =K57+K56 -> 70.808681 | L58: =L57+L56 -> 91.691561 | M58: =M57+M56 -> 127.14773 | ... P58: =P57+P56 -> 255.22602
B60: Balance sheet (31 March)
B61: Cash | C61: ₹ lakh | F61: =F58 -> 19.1085 | G61: =G58 -> 3.0794934 | H61: =H58 -> 8.7494423 | I61: =I58 -> 29.499385 | J61: =J58 -> 48.616324 | K61: =K58 -> 70.808681 | L61: =L58 -> 91.691561 | M61: =M58 -> 127.14773 | ... P61: =P58 -> 255.22602
B62: Receivables | C62: ₹ lakh | F62: =F190 -> 0 | G62: =G190 -> 0.30157151 | H62: =H190 -> 0.41408088 | I62: =I190 -> 0.51151167 | J62: =J190 -> 0.55051444 | K62: =K190 -> 0.59249116 | L62: =L190 -> 0.63766861 | M62: =M190 -> 0.68629084 | ... P62: =P190 -> 0.85555454
B63: Inventory | C63: ₹ lakh | F63: =F191 -> 0 | G63: =G191 -> 2.2080986 | H63: =H191 -> 3.0065526 | I63: =I191 -> 3.6832747 | J63: =J191 -> 3.9316695 | K63: =K191 -> 4.1972692 | L63: =L191 -> 4.4812389 | M63: =M191 -> 4.7848243 | ... P63: =P191 -> 5.8275971
B64: Rent deposit | C64: ₹ lakh | F64: =F196 -> 4.6 | G64: =G196 -> 4.6 | H64: =H196 -> 4.6 | I64: =I196 -> 4.6 | J64: =J196 -> 4.6 | K64: =K196 -> 4.6 | L64: =L196 -> 4.6 | M64: =M196 -> 4.6 | ... P64: =P196 -> 4.6
B65: Fixed assets, net (incl. property) | C65: ₹ lakh | F65: =F159 -> 66.465 | G65: =G159 -> 59.872272 | H65: =H159 -> 53.551703 | I65: =I159 -> 47.30734 | J65: =J159 -> 40.732914 | K65: =K159 -> 34.275759 | L65: =L159 -> 38.927609 | M65: =M159 -> 29.692904 | ... P65: =P159 -> 14.482638
B66: Total assets | C66: ₹ lakh | F66: =SUM(F61:F65) -> 90.1735 | G66: =SUM(G61:G65) -> 70.061435 | H66: =SUM(H61:H65) -> 70.321779 | I66: =SUM(I61:I65) -> 85.601511 | J66: =SUM(J61:J65) -> 98.431422 | K66: =SUM(K61:K65) -> 114.4742 | L66: =SUM(L61:L65) -> 140.33808 | M66: =SUM(M61:M65) -> 166.91174 | ... P66: =SUM(P61:P65) -> 280.99181
B67: Payables | C67: ₹ lakh | F67: =F192 -> 0 | G67: =G192 -> 1.3028505 | H67: =H192 -> 1.7794128 | I67: =I192 -> 2.1865849 | J67: =J192 -> 2.3411414 | K67: =K192 -> 2.5068321 | L67: =L192 -> 2.684451 | M67: =M192 -> 2.8748496 | ... P67: =P192 -> 3.532389
B68: Cash credit | C68: ₹ lakh | F68: =F209 -> 0 | G68: =G209 -> 0 | H68: =H209 -> 0 | I68: =I209 -> 0 | J68: =J209 -> 0 | K68: =K209 -> 0 | L68: =L209 -> 0 | M68: =M209 -> 0 | ... P68: =P209 -> 0
B69: Term loan | C69: ₹ lakh | F69: =F203 -> 33.2 | G69: =G203 -> 26.56 | H69: =H203 -> 19.92 | I69: =I203 -> 13.28 | J69: =J203 -> 6.64 | K69: =K203 -> 0 | L69: =L203 -> 0 | M69: =M203 -> 0 | ... P69: =P203 -> 0
B70: Deferred tax liability / (asset), net | C70: ₹ lakh | F70: =F173 -> 0 | G70: =G173 -> 0.14955522 | H70: =H173 -> -0.042536403 | I70: =I173 -> -0.5312724 | J70: =J173 -> -1.293265 | K70: =K173 -> -2.1878329 | L70: =L173 -> -3.1025679 | M70: =M173 -> -4.5601788 | ... P70: =P173 -> -6.7442859
B71: Total liabilities | C71: ₹ lakh | F71: =SUM(F67:F70) -> 33.2 | G71: =SUM(G67:G70) -> 28.012406 | H71: =SUM(H67:H70) -> 21.656876 | I71: =SUM(I67:I70) -> 14.935312 | J71: =SUM(J67:J70) -> 7.6878764 | K71: =SUM(K67:K70) -> 0.31899918 | L71: =SUM(L67:L70) -> -0.41811683 | M71: =SUM(M67:M70) -> -1.6853292 | ... P71: =SUM(P67:P70) -> -3.2118969
B72: Share capital | C72: ₹ lakh | F72: =F217 -> 68.028 | G72: =G217 -> 68.028 | H72: =H217 -> 68.028 | I72: =I217 -> 68.028 | J72: =J217 -> 68.028 | K72: =K217 -> 68.028 | L72: =L217 -> 68.028 | M72: =M217 -> 68.028 | ... P72: =P217 -> 68.028
B73: Retained earnings | C73: ₹ lakh | F73: =F221 -> -11.0545 | G73: =G221 -> -25.978971 | H73: =H221 -> -19.363097 | I73: =I221 -> 2.6381987 | J73: =J221 -> 22.715546 | K73: =K221 -> 46.127201 | L73: =L221 -> 72.728194 | M73: =M221 -> 100.56907 | ... P73: =P221 -> 216.17571
B74: Shareholders' equity | C74: ₹ lakh | F74: =F72+F73 -> 56.9735 | G74: =G72+G73 -> 42.049029 | H74: =H72+H73 -> 48.664903 | I74: =I72+I73 -> 70.666199 | J74: =J72+J73 -> 90.743546 | K74: =K72+K73 -> 114.1552 | L74: =L72+L73 -> 140.75619 | M74: =M72+M73 -> 168.59707 | ... P74: =P72+P73 -> 284.20371
B75: Total liabilities & equity | C75: ₹ lakh | F75: =F71+F74 -> 90.1735 | G75: =G71+G74 -> 70.061435 | H75: =H71+H74 -> 70.321779 | I75: =I71+I74 -> 85.601511 | J75: =J71+J74 -> 98.431422 | K75: =K71+K74 -> 114.4742 | L75: =L71+L74 -> 140.33808 | M75: =M71+M74 -> 166.91174 | ... P75: =P71+P74 -> 280.99181
B76: Check (assets - liabilities - equity) | C76: ₹ lakh | F76: =ROUND(F66-F75,4) -> 0 | G76: =ROUND(G66-G75,4) -> 0 | H76: =ROUND(H66-H75,4) -> 0 | I76: =ROUND(I66-I75,4) -> 0 | J76: =ROUND(J66-J75,4) -> 0 | K76: =ROUND(K66-K75,4) -> 0 | L76: =ROUND(L66-L75,4) -> 0 | M76: =ROUND(M66-M75,4) -> 0 | ... P76: =ROUND(P66-P75,4) -> 0
B78: Schedule 1: Revenue
B79: Ramp-up (Live driver) | C79: % | G79: =Inputs!G35 -> 0.65 | H79: =Inputs!H35 -> 0.85 | I79: =Inputs!I35 -> 1 | J79: =Inputs!J35 -> 1 | K79: =Inputs!K35 -> 1 | L79: =Inputs!L35 -> 1 | M79: =Inputs!M35 -> 1 | N79: =Inputs!N35 -> 1 | ... P79: =Inputs!P35 -> 1
B80: Volume growth (Live driver) | C80: % | G80: =Inputs!G45 -> 0 | H80: =Inputs!H45 -> 0 | I80: =Inputs!I45 -> 0 | J80: =Inputs!J45 -> 0.025 | K80: =Inputs!K45 -> 0.025 | L80: =Inputs!L45 -> 0.025 | M80: =Inputs!M45 -> 0.025 | N80: =Inputs!N45 -> 0.025 | ... P80: =Inputs!P45 -> 0.025
B81: Location growth premium (Y2-Y6) | C81: % | G81: =IF(AND(G6>=2,G6<=6),Locations!$H$17,0) -> 0 | H81: =IF(AND(H6>=2,H6<=6),Locations!$H$17,0) -> 0 | I81: =IF(AND(I6>=2,I6<=6),Locations!$H$17,0) -> 0 | J81: =IF(AND(J6>=2,J6<=6),Locations!$H$17,0) -> 0 | K81: =IF(AND(K6>=2,K6<=6),Locations!$H$17,0) -> 0 | L81: =IF(AND(L6>=2,L6<=6),Locations!$H$17,0) -> 0 | M81: =IF(AND(M6>=2,M6<=6),Locations!$H$17,0) -> 0 | N81: =IF(AND(N6>=2,N6<=6),Locations!$H$17,0) -> 0 | ... P81: =IF(AND(P6>=2,P6<=6),Locations!$H$17,0) -> 0
B82: Volume index | C82: x | G82: =G7 -> 1 | H82: =G82*(1+H80)*(1+H81) -> 1 | I82: =H82*(1+I80)*(1+I81) -> 1 | J82: =I82*(1+J80)*(1+J81) -> 1.025 | K82: =J82*(1+K80)*(1+K81) -> 1.050625 | L82: =K82*(1+L80)*(1+L81) -> 1.0768906 | M82: =L82*(1+M80)*(1+M81) -> 1.1038129 | N82: =M82*(1+N80)*(1+N81) -> 1.1314082 | O82: =N82*(1+O80)*(1+O81) -> 1.1596934 | P82: =O82*(1+P80)*(1+P81) -> 1.1886858
B83: Bills per day, demand | C83: # | G83: =Locations!$H$13*Inputs!$D$55*(1+Sourcing!$J$50)*Scenarios!$D$36*G79*G82 -> 91 | H83: =Locations!$H$13*Inputs!$D$55*(1+Sourcing!$J$50)*Scenarios!$D$36*H79*H82 -> 119 | I83: =Locations!$H$13*Inputs!$D$55*(1+Sourcing!$J$50)*Scenarios!$D$36*I79*I82 -> 140 | J83: =Locations!$H$13*Inputs!$D$55*(1+Sourcing!$J$50)*Scenarios!$D$36*J79*J82 -> 143.5 | K83: =Locations!$H$13*Inputs!$D$55*(1+Sourcing!$J$50)*Scenarios!$D$36*K79*K82 -> 147.0875 | L83: =Locations!$H$13*Inputs!$D$55*(1+Sourcing!$J$50)*Scenarios!$D$36*L79*L82 -> 150.76469 | M83: =Locations!$H$13*Inputs!$D$55*(1+Sourcing!$J$50)*Scenarios!$D$36*M79*M82 -> 154.5338 | N83: =Locations!$H$13*Inputs!$D$55*(1+Sourcing!$J$50)*Scenarios!$D$36*N79*N82 -> 158.39715 | ... P83: =Locations!$H$13*Inputs!$D$55*(1+Sourcing!$J$50)*Scenarios!$D$36*P79*P82 -> 166.41601
B84: Bills per day, seating capacity | C84: # | G84: =Locations!$H$7*Inputs!$D$74/(1-Inputs!$D$67-Locations!$H$16)*G7 -> 400 | H84: =Locations!$H$7*Inputs!$D$74/(1-Inputs!$D$67-Locations!$H$16)*H7 -> 400 | I84: =Locations!$H$7*Inputs!$D$74/(1-Inputs!$D$67-Locations!$H$16)*I7 -> 400 | J84: =Locations!$H$7*Inputs!$D$74/(1-Inputs!$D$67-Locations!$H$16)*J7 -> 400 | K84: =Locations!$H$7*Inputs!$D$74/(1-Inputs!$D$67-Locations!$H$16)*K7 -> 400 | L84: =Locations!$H$7*Inputs!$D$74/(1-Inputs!$D$67-Locations!$H$16)*L7 -> 400 | M84: =Locations!$H$7*Inputs!$D$74/(1-Inputs!$D$67-Locations!$H$16)*M7 -> 400 | N84: =Locations!$H$7*Inputs!$D$74/(1-Inputs!$D$67-Locations!$H$16)*N7 -> 400 | ... P84: =Locations!$H$7*Inputs!$D$74/(1-Inputs!$D$67-Locations!$H$16)*P7 -> 400
B85: Bills per day | C85: # | G85: =MIN(G83,G84) -> 91 | H85: =MIN(H83,H84) -> 119 | I85: =MIN(I83,I84) -> 140 | J85: =MIN(J83,J84) -> 143.5 | K85: =MIN(K83,K84) -> 147.0875 | L85: =MIN(L83,L84) -> 150.76469 | M85: =MIN(M83,M84) -> 154.5338 | N85: =MIN(N83,N84) -> 158.39715 | ... P85: =MIN(P83,P84) -> 166.41601
B86: Capacity utilisation | C86: % | G86: =IF(G84>0,G85/G84,0) -> 0.2275 | H86: =IF(H84>0,H85/H84,0) -> 0.2975 | I86: =IF(I84>0,I85/I84,0) -> 0.35 | J86: =IF(J84>0,J85/J84,0) -> 0.35875 | K86: =IF(K84>0,K85/K84,0) -> 0.36771875 | L86: =IF(L84>0,L85/L84,0) -> 0.37691172 | M86: =IF(M84>0,M85/M84,0) -> 0.38633451 | N86: =IF(N84>0,N85/N84,0) -> 0.39599287 | ... P86: =IF(P84>0,P85/P84,0) -> 0.41604001
B87: Operating days | C87: days | G87: =Locations!$H$15*G7 -> 360 | H87: =Locations!$H$15*H7 -> 360 | I87: =Locations!$H$15*I7 -> 360 | J87: =Locations!$H$15*J7 -> 360 | K87: =Locations!$H$15*K7 -> 360 | L87: =Locations!$H$15*L7 -> 360 | M87: =Locations!$H$15*M7 -> 360 | N87: =Locations!$H$15*N7 -> 360 | ... P87: =Locations!$H$15*P7 -> 360
B88: Bills per year | C88: # | G88: =G85*G87 -> 32760 | H88: =H85*H87 -> 42840 | I88: =I85*I87 -> 50400 | J88: =J85*J87 -> 51660 | K88: =K85*K87 -> 52951.5 | L88: =L85*L87 -> 54275.287 | M88: =M85*M87 -> 55632.17 | N88: =N85*N87 -> 57022.974 | ... P88: =P85*P87 -> 59909.762
B89: Average bill value (ex-GST) | C89: ₹ | G89: =Locations!$H$14*(1+Sourcing!$J$49)*Scenarios!$D$37 -> 320 | H89: =G89*(1+H90) -> 336 | I89: =H89*(1+I90) -> 352.8 | J89: =I89*(1+J90) -> 370.44 | K89: =J89*(1+K90) -> 388.962 | L89: =K89*(1+L90) -> 408.4101 | M89: =L89*(1+M90) -> 428.83061 | N89: =M89*(1+N90) -> 450.27214 | O89: =N89*(1+O90) -> 472.78574 | P89: =O89*(1+P90) -> 496.42503
B90: Menu price increase (Live driver) | C90: % | G90: =Inputs!G40 -> 0 | H90: =Inputs!H40 -> 0.05 | I90: =Inputs!I40 -> 0.05 | J90: =Inputs!J40 -> 0.05 | K90: =Inputs!K40 -> 0.05 | L90: =Inputs!L40 -> 0.05 | M90: =Inputs!M40 -> 0.05 | N90: =Inputs!N40 -> 0.05 | ... P90: =Inputs!P40 -> 0.05
B91: Café revenue | C91: ₹ lakh | F91: =F88*F89/Lakh -> 0 | G91: =G88*G89/Lakh -> 104.832 | H91: =H88*H89/Lakh -> 143.9424 | I91: =I88*I89/Lakh -> 177.8112 | J91: =J88*J89/Lakh -> 191.3693 | K91: =K88*K89/Lakh -> 205.96121 | L91: =L88*L89/Lakh -> 221.66576 | M91: =M88*M89/Lakh -> 238.56777 | ... P91: =P88*P89/Lakh -> 297.40705
B92: Beverages | C92: ₹ lakh | F92: =F91*Inputs!$D$60 -> 0 | G92: =G91*Inputs!$D$60 -> 64.99584 | H92: =H91*Inputs!$D$60 -> 89.244288 | I92: =I91*Inputs!$D$60 -> 110.24294 | J92: =J91*Inputs!$D$60 -> 118.64897 | K92: =K91*Inputs!$D$60 -> 127.69595 | L92: =L91*Inputs!$D$60 -> 137.43277 | M92: =M91*Inputs!$D$60 -> 147.91202 | ... P92: =P91*Inputs!$D$60 -> 184.39237
B93: Food | C93: ₹ lakh | F93: =F91*Inputs!$D$77 -> 0 | G93: =G91*Inputs!$D$77 -> 31.4496 | H93: =H91*Inputs!$D$77 -> 43.18272 | I93: =I91*Inputs!$D$77 -> 53.34336 | J93: =J91*Inputs!$D$77 -> 57.410791 | K93: =K91*Inputs!$D$77 -> 61.788364 | L93: =L91*Inputs!$D$77 -> 66.499727 | M93: =M91*Inputs!$D$77 -> 71.570331 | ... P93: =P91*Inputs!$D$77 -> 89.222116
B94: Retail beans & merchandise | C94: ₹ lakh | F94: =F91*Inputs!$D$76 -> 0 | G94: =G91*Inputs!$D$76 -> 8.38656 | H94: =H91*Inputs!$D$76 -> 11.515392 | I94: =I91*Inputs!$D$76 -> 14.224896 | J94: =J91*Inputs!$D$76 -> 15.309544 | K94: =K91*Inputs!$D$76 -> 16.476897 | L94: =L91*Inputs!$D$76 -> 17.73326 | M94: =M91*Inputs!$D$76 -> 19.085422 | ... P94: =P91*Inputs!$D$76 -> 23.792564
B95: Wholesale beans sold (in-house roastery only) | C95: kg/month | G95: =Inputs!$D$21*Scenarios!$D$42*Locations!$H$19*Inputs!G52*(1+Inputs!$D$72)^MAX(0,G6-3) -> 0 | H95: =Inputs!$D$21*Scenarios!$D$42*Locations!$H$19*Inputs!H52*(1+Inputs!$D$72)^MAX(0,H6-3) -> 0 | I95: =Inputs!$D$21*Scenarios!$D$42*Locations!$H$19*Inputs!I52*(1+Inputs!$D$72)^MAX(0,I6-3) -> 0 | J95: =Inputs!$D$21*Scenarios!$D$42*Locations!$H$19*Inputs!J52*(1+Inputs!$D$72)^MAX(0,J6-3) -> 0 | K95: =Inputs!$D$21*Scenarios!$D$42*Locations!$H$19*Inputs!K52*(1+Inputs!$D$72)^MAX(0,K6-3) -> 0 | L95: =Inputs!$D$21*Scenarios!$D$42*Locations!$H$19*Inputs!L52*(1+Inputs!$D$72)^MAX(0,L6-3) -> 0 | M95: =Inputs!$D$21*Scenarios!$D$42*Locations!$H$19*Inputs!M52*(1+Inputs!$D$72)^MAX(0,M6-3) -> 0 | N95: =Inputs!$D$21*Scenarios!$D$42*Locations!$H$19*Inputs!N52*(1+Inputs!$D$72)^MAX(0,N6-3) -> 0 | ... P95: =Inputs!$D$21*Scenarios!$D$42*Locations!$H$19*Inputs!P52*(1+Inputs!$D$72)^MAX(0,P6-3) -> 0
B96: Wholesale beans sold | C96: kg/yr | G96: =G95*12 -> 0 | H96: =H95*12 -> 0 | I96: =I95*12 -> 0 | J96: =J95*12 -> 0 | K96: =K95*12 -> 0 | L96: =L95*12 -> 0 | M96: =M95*12 -> 0 | N96: =N95*12 -> 0 | ... P96: =P95*12 -> 0
B97: Wholesale revenue | C97: ₹ lakh | G97: =G96*Sourcing!$J$48*G8/Lakh -> 0 | H97: =H96*Sourcing!$J$48*H8/Lakh -> 0 | I97: =I96*Sourcing!$J$48*I8/Lakh -> 0 | J97: =J96*Sourcing!$J$48*J8/Lakh -> 0 | K97: =K96*Sourcing!$J$48*K8/Lakh -> 0 | L97: =L96*Sourcing!$J$48*L8/Lakh -> 0 | M97: =M96*Sourcing!$J$48*M8/Lakh -> 0 | N97: =N96*Sourcing!$J$48*N8/Lakh -> 0 | ... P97: =P96*Sourcing!$J$48*P8/Lakh -> 0
B98: Total revenue | C98: ₹ lakh | F98: =F91+F97 -> 0 | G98: =G91+G97 -> 104.832 | H98: =H91+H97 -> 143.9424 | I98: =I91+I97 -> 177.8112 | J98: =J91+J97 -> 191.3693 | K98: =K91+K97 -> 205.96121 | L98: =L91+L97 -> 221.66576 | M98: =M91+M97 -> 238.56777 | ... P98: =P91+P97 -> 297.40705
B100: Schedule 2: Cost of goods sold
B101: Beverages sold | C101: # | G101: =G88*Inputs!$D$78 -> 29543.564 | H101: =H88*Inputs!$D$78 -> 38633.891 | I101: =I88*Inputs!$D$78 -> 45451.636 | J101: =J88*Inputs!$D$78 -> 46587.927 | K101: =K88*Inputs!$D$78 -> 47752.625 | L101: =L88*Inputs!$D$78 -> 48946.441 | M101: =M88*Inputs!$D$78 -> 50170.102 | N101: =N88*Inputs!$D$78 -> 51424.355 | ... P101: =P88*Inputs!$D$78 -> 54027.713
B102: Coffee used in the café | C102: kg | G102: =G101*Inputs!$D$64*Inputs!$D$65/1000 -> 452.01652 | H102: =H101*Inputs!$D$64*Inputs!$D$65/1000 -> 591.09853 | I102: =I101*Inputs!$D$64*Inputs!$D$65/1000 -> 695.41004 | J102: =J101*Inputs!$D$64*Inputs!$D$65/1000 -> 712.79529 | K102: =K101*Inputs!$D$64*Inputs!$D$65/1000 -> 730.61517 | L102: =L101*Inputs!$D$64*Inputs!$D$65/1000 -> 748.88055 | M102: =M101*Inputs!$D$64*Inputs!$D$65/1000 -> 767.60256 | N102: =N101*Inputs!$D$64*Inputs!$D$65/1000 -> 786.79263 | ... P102: =P101*Inputs!$D$64*Inputs!$D$65/1000 -> 826.624
B103: Retail beans sold | C103: kg | G103: =G94*Lakh/(Sourcing!$J$47*G8) -> 349.44 | H103: =H94*Lakh/(Sourcing!$J$47*H8) -> 456.96 | I103: =I94*Lakh/(Sourcing!$J$47*I8) -> 537.6 | J103: =J94*Lakh/(Sourcing!$J$47*J8) -> 551.04 | K103: =K94*Lakh/(Sourcing!$J$47*K8) -> 564.816 | L103: =L94*Lakh/(Sourcing!$J$47*L8) -> 578.9364 | M103: =M94*Lakh/(Sourcing!$J$47*M8) -> 593.40981 | N103: =N94*Lakh/(Sourcing!$J$47*N8) -> 608.24506 | ... P103: =P94*Lakh/(Sourcing!$J$47*P8) -> 639.03746
B104: Roasted coffee to source (own label) | C104: kg | G104: =G102+Inputs!$D$22*G103+G96 -> 801.45652 | H104: =H102+Inputs!$D$22*H103+H96 -> 1048.0585 | I104: =I102+Inputs!$D$22*I103+I96 -> 1233.01 | J104: =J102+Inputs!$D$22*J103+J96 -> 1263.8353 | K104: =K102+Inputs!$D$22*K103+K96 -> 1295.4312 | L104: =L102+Inputs!$D$22*L103+L96 -> 1327.8169 | M104: =M102+Inputs!$D$22*M103+M96 -> 1361.0124 | N104: =N102+Inputs!$D$22*N103+N96 -> 1395.0377 | ... P104: =P102+Inputs!$D$22*P103+P96 -> 1465.6615
B105: Green coffee to buy (toll / in-house) | C105: kg | G105: =IF(Inputs!$D$17>=2,G104/(1-Sourcing!$D$6),0) -> 954.11491 | H105: =IF(Inputs!$D$17>=2,H104/(1-Sourcing!$D$6),0) -> 1247.6887 | I105: =IF(Inputs!$D$17>=2,I104/(1-Sourcing!$D$6),0) -> 1467.8691 | J105: =IF(Inputs!$D$17>=2,J104/(1-Sourcing!$D$6),0) -> 1504.5658 | K105: =IF(Inputs!$D$17>=2,K104/(1-Sourcing!$D$6),0) -> 1542.18 | L105: =IF(Inputs!$D$17>=2,L104/(1-Sourcing!$D$6),0) -> 1580.7345 | M105: =IF(Inputs!$D$17>=2,M104/(1-Sourcing!$D$6),0) -> 1620.2528 | N105: =IF(Inputs!$D$17>=2,N104/(1-Sourcing!$D$6),0) -> 1660.7591 | ... P105: =IF(Inputs!$D$17>=2,P104/(1-Sourcing!$D$6),0) -> 1744.8351
B106: Green-coffee price index (Live x override) | C106: x | G106: =Inputs!G50*Scenarios!$D$39 -> 1 | H106: =Inputs!H50*Scenarios!$D$39 -> 1.03 | I106: =Inputs!I50*Scenarios!$D$39 -> 1.0609 | J106: =Inputs!J50*Scenarios!$D$39 -> 1.0927 | K106: =Inputs!K50*Scenarios!$D$39 -> 1.1255 | L106: =Inputs!L50*Scenarios!$D$39 -> 1.1593 | M106: =Inputs!M50*Scenarios!$D$39 -> 1.1941 | N106: =Inputs!N50*Scenarios!$D$39 -> 1.2299 | ... P106: =Inputs!P50*Scenarios!$D$39 -> 1.3048
...

Sheet DCF
B1: DCF valuation (FCFF)
B2: Valuation date 31 March 2027 (end of Y0). Y0 investment is undiscounted; Y1-Y10 discounted at WACC; Gordon-growth terminal value at Y10.
B3: ="Model running: "&Inputs!$D$23 -> Model running: Prahladnagar | Rent | Toll roasting | Specialty mix | Base case
B5: ₹ lakh unless stated | C5: Units | D5: Value | F5: =Model!F5 -> 2027 | G5: =Model!G5 -> 2028 | H5: =Model!H5 -> 2029 | I5: =Model!I5 -> 2030 | J5: =Model!J5 -> 2031 | K5: =Model!K5 -> 2032 | L5: =Model!L5 -> 2033 | M5: =Model!M5 -> 2034 | ... P5: =Model!P5 -> 2037
B6: Period (Y0 = pre-opening fit-out year) | F6: =F5-Inputs!$D$26 -> 0 | G6: =G5-Inputs!$D$26 -> 1 | H6: =H5-Inputs!$D$26 -> 2 | I6: =I5-Inputs!$D$26 -> 3 | J6: =J5-Inputs!$D$26 -> 4 | K6: =K5-Inputs!$D$26 -> 5 | L6: =L5-Inputs!$D$26 -> 6 | M6: =M5-Inputs!$D$26 -> 7 | ... P6: =P5-Inputs!$D$26 -> 10
B7: Free cash flow to the firm
B8: EBITDA | C8: ₹ lakh | F8: =Model!F29 -> -11.0545 | G8: =Model!G29 -> -3.722047 | H8: =Model!H29 -> 17.701906 | I8: =Model!I29 -> 33.683883 | J8: =Model!J29 -> 36.555685 | K8: =Model!K29 -> 39.61794 | L8: =Model!L29 -> 42.879726 | M8: =Model!M29 -> 46.350071 | ... P8: =Model!P29 -> 58.095121
B9: Less: depreciation | C9: ₹ lakh | F9: =-Model!F157 -> 0 | G9: =-Model!G157 -> -8.1652083 | H9: =-Model!H157 -> -8.4797043 | I9: =-Model!I157 -> -8.9115315 | J9: =-Model!J157 -> -9.4449651 | K9: =-Model!K157 -> -9.546573 | L9: =-Model!L157 -> -10.164457 | M9: =-Model!M157 -> -12.813222 | ... P9: =-Model!P157 -> -5.8961331
B10: EBIT | C10: ₹ lakh | F10: =F8+F9 -> -11.0545 | G10: =G8+G9 -> -11.887255 | H10: =H8+H9 -> 9.222202 | I10: =I8+I9 -> 24.772351 | J10: =J8+J9 -> 27.11072 | K10: =K8+K9 -> 30.071367 | L10: =L8+L9 -> 32.71527 | M10: =M8+M9 -> 33.536849 | ... P10: =P8+P9 -> 52.198988
B11: Unlevered tax (as if no debt)
B12: EBIT + book dep - tax dep | C12: ₹ lakh | F12: =F10+Model!F157-Model!F171 -> -11.0545 | G12: =G10+Model!G157-Model!G171 -> -12.481483 | H12: =H10+Model!H157-Model!H171 -> 9.9854395 | I12: =I10+Model!I157-Model!I171 -> 26.714246 | J12: =J10+Model!J157-Model!J171 -> 30.138345 | K12: =K10+Model!K157-Model!K171 -> 33.625754 | L12: =L10+Model!L157-Model!L171 -> 36.349785 | M12: =M10+Model!M157-Model!M171 -> 39.328374 | ... P12: =P10+Model!P157-Model!P171 -> 52.019254
B13: Losses brought forward | C13: ₹ lakh | G13: =F16 -> 11.0545 | H13: =G16 -> 23.535983 | I13: =H16 -> 13.550544 | J13: =I16 -> 0 | K13: =J16 -> 0 | L13: =K16 -> 0 | M13: =L16 -> 0 | N13: =M16 -> 0 | ... P13: =O16 -> 0
B14: Losses added | C14: ₹ lakh | F14: =MAX(0,-F12) -> 11.0545 | G14: =MAX(0,-G12) -> 12.481483 | H14: =MAX(0,-H12) -> 0 | I14: =MAX(0,-I12) -> 0 | J14: =MAX(0,-J12) -> 0 | K14: =MAX(0,-K12) -> 0 | L14: =MAX(0,-L12) -> 0 | M14: =MAX(0,-M12) -> 0 | ... P14: =MAX(0,-P12) -> 0
B15: Losses used | C15: ₹ lakh | F15: =MIN(N(F13),MAX(0,F12)) -> 0 | G15: =MIN(N(G13),MAX(0,G12)) -> 0 | H15: =MIN(N(H13),MAX(0,H12)) -> 9.9854395 | I15: =MIN(N(I13),MAX(0,I12)) -> 13.550544 | J15: =MIN(N(J13),MAX(0,J12)) -> 0 | K15: =MIN(N(K13),MAX(0,K12)) -> 0 | L15: =MIN(N(L13),MAX(0,L12)) -> 0 | M15: =MIN(N(M13),MAX(0,M12)) -> 0 | ... P15: =MIN(N(P13),MAX(0,P12)) -> 0
B16: Losses carried forward | C16: ₹ lakh | F16: =F13+F14-F15 -> 11.0545 | G16: =G13+G14-G15 -> 23.535983 | H16: =H13+H14-H15 -> 13.550544 | I16: =I13+I14-I15 -> 0 | J16: =J13+J14-J15 -> 0 | K16: =K13+K14-K15 -> 0 | L16: =L13+L14-L15 -> 0 | M16: =M13+M14-M15 -> 0 | ... P16: =P13+P14-P15 -> 0
B17: Unlevered tax | C17: ₹ lakh | F17: =(MAX(0,F12)-F15)*TaxRate -> 0 | G17: =(MAX(0,G12)-G15)*TaxRate -> 0 | H17: =(MAX(0,H12)-H15)*TaxRate -> 0 | I17: =(MAX(0,I12)-I15)*TaxRate -> 3.3130406 | J17: =(MAX(0,J12)-J15)*TaxRate -> 7.5852186 | K17: =(MAX(0,K12)-K15)*TaxRate -> 8.4629297 | L17: =(MAX(0,L12)-L15)*TaxRate -> 9.148514 | M17: =(MAX(0,M12)-M15)*TaxRate -> 9.8981651 | ... P17: =(MAX(0,P12)-P15)*TaxRate -> 13.092206
B18: Free cash flow
B19: NOPAT (EBIT - unlevered tax) | C19: ₹ lakh | F19: =F10-F17 -> -11.0545 | G19: =G10-G17 -> -11.887255 | H19: =H10-H17 -> 9.222202 | I19: =I10-I17 -> 21.459311 | J19: =J10-J17 -> 19.525501 | K19: =K10-K17 -> 21.608438 | L19: =L10-L17 -> 23.566756 | M19: =M10-M17 -> 23.638684 | ... P19: =P10-P17 -> 39.106782
B20: Add: depreciation | C20: ₹ lakh | F20: =Model!F157 -> 0 | G20: =Model!G157 -> 8.1652083 | H20: =Model!H157 -> 8.4797043 | I20: =Model!I157 -> 8.9115315 | J20: =Model!J157 -> 9.4449651 | K20: =Model!K157 -> 9.546573 | L20: =Model!L157 -> 10.164457 | M20: =Model!M157 -> 12.813222 | ... P20: =Model!P157 -> 5.8961331
B21: Less: capex incl. property | C21: ₹ lakh | F21: =-Model!F148 -> -66.465 | G21: =-Model!G148 -> -1.57248 | H21: =-Model!H148 -> -2.159136 | I21: =-Model!I148 -> -2.667168 | J21: =-Model!J148 -> -2.8705396 | K21: =-Model!K148 -> -3.0894182 | L21: =-Model!L148 -> -14.816306 | M21: =-Model!M148 -> -3.5785165 | ... P21: =-Model!P148 -> -4.4611058
B22: Less: increase in working capital | C22: ₹ lakh | F22: =-Model!F194 -> 0 | G22: =-Model!G194 -> -1.2068196 | H22: =-Model!H194 -> -0.43440114 | I22: =-Model!I194 -> -0.36698081 | J22: =-Model!J194 -> -0.13284104 | K22: =-Model!K194 -> -0.14188566 | L22: =-Model!L194 -> -0.15152823 | M22: =-Model!M194 -> -0.16180917 | ... P22: =-Model!P194 -> -0.1971548
B23: Less: rent deposit | C23: ₹ lakh | F23: =-Model!F195 -> -4.6 | G23: =-Model!G195 -> 0 | H23: =-Model!H195 -> 0 | I23: =-Model!I195 -> 0 | J23: =-Model!J195 -> 0 | K23: =-Model!K195 -> 0 | L23: =-Model!L195 -> 0 | M23: =-Model!M195 -> 0 | ... P23: =-Model!P195 -> 0
B24: Free cash flow to firm | C24: ₹ lakh | F24: =SUM(F19:F23) -> -82.1195 | G24: =SUM(G19:G23) -> -6.5013466 | H24: =SUM(H19:H23) -> 15.108369 | I24: =SUM(I19:I23) -> 27.336694 | J24: =SUM(J19:J23) -> 25.967086 | K24: =SUM(K19:K23) -> 27.923707 | L24: =SUM(L19:L23) -> 18.763378 | M24: =SUM(M19:M23) -> 32.71158 | ... P24: =SUM(P19:P23) -> 40.344655
B25: Discount period | C25: years | F25: =F6 -> 0 | G25: =G6-0.5*Inputs!$D$163 -> 1 | H25: =H6-0.5*Inputs!$D$163 -> 2 | I25: =I6-0.5*Inputs!$D$163 -> 3 | J25: =J6-0.5*Inputs!$D$163 -> 4 | K25: =K6-0.5*Inputs!$D$163 -> 5 | L25: =L6-0.5*Inputs!$D$163 -> 6 | M25: =M6-0.5*Inputs!$D$163 -> 7 | N25: =N6-0.5*Inputs!$D$163 -> 8 | ... P25: =P6-0.5*Inputs!$D$163 -> 10
B26: Discount factor | C26: x | F26: =1/(1+$D$41)^F25 -> 1 | G26: =1/(1+$D$41)^G25 -> 0.86091563 | H26: =1/(1+$D$41)^H25 -> 0.74117573 | I26: =1/(1+$D$41)^I25 -> 0.63808977 | J26: =1/(1+$D$41)^J25 -> 0.54934146 | K26: =1/(1+$D$41)^K25 -> 0.47293665 | L26: =1/(1+$D$41)^L25 -> 0.40715856 | M26: =1/(1+$D$41)^M25 -> 0.35052917 | ... P26: =1/(1+$D$41)^P25 -> 0.22366908
B27: Present value of FCFF | C27: ₹ lakh | F27: =F24*F26 -> -82.1195 | G27: =G24*G26 -> -5.5971109 | H27: =H24*H26 -> 11.197957 | I27: =I24*I26 -> 17.443264 | J27: =J24*J26 -> 14.264797 | K27: =K24*K26 -> 13.206144 | L27: =L24*L26 -> 7.6396697 | M27: =M24*M26 -> 11.466363 | ... P27: =P24*P26 -> 9.0238517
B29: Cost of capital
B30: Risk-free rate | C30: % | D30: =Inputs!$D$155 -> 0.0729
B31: Equity risk premium | C31: % | D31: =Inputs!$D$156 -> 0.0708
B32: Unlevered beta | C32: x | D32: =Inputs!$D$157 -> 0.8
B33: Debt / (debt + equity), from funding plan | C33: % | D33: =Capex!$G$59 -> 0.3279725
B34: Debt / equity | C34: x | D34: =IF($D$33<1,$D$33/(1-$D$33),0) -> 0.48803434
B35: Relevered beta | C35: x | D35: =$D$32*(1+(1-TaxRate)*$D$34) -> 1.0921647
B36: Size & single-outlet premium | C36: % | D36: =Inputs!$D$158 -> 0.05
B37: Cost of equity | C37: % | D37: =$D$30+$D$35*$D$31+$D$36 -> 0.20022526
B38: Cost of debt, pre-tax | C38: % | D38: =Capex!$G$60 -> 0.11
B39: Cost of debt, after tax | C39: % | D39: =$D$38*(1-TaxRate) -> 0.0823152
B40: WACC, calculated | C40: % | D40: =(1-$D$33)*$D$37+$D$33*$D$39 -> 0.161554
B41: WACC used (incl. any Scenarios-sheet change) | C41: % | D41: =$D$40+Scenarios!$D$43 -> 0.161554
B42: Terminal growth used | C42: % | D42: =Scenarios!$D$44 -> 0.04
B44: Terminal value at Y10
B45: Terminal year | C45: # | D45: =MAX($F$6:$P$6) -> 10
B46: Own case: market rent the site would pay in Y11 | C46: ₹ lakh | D46: =Inputs!$D$20*Capex!$G$26*Locations!$H$8*Scenarios!$D$38*12*(1+Inputs!$D$112)^$D$45/Lakh -> 0
B47: Normalised refurbishment per year (cost / cycle) | C47: ₹ lakh | D47: =Inputs!$D$126*(Capex!$D$37+Capex!$D$39)*Model!P8*(1+Inputs!$D$73)/Inputs!$D$125 -> 2.44436
B48: Operating FCFF in Y11 (after notional rent if owned) | C48: ₹ lakh | D48: =(P24+Model!P124*(1-TaxRate))*(1+$D$42)-$D$46*(1-TaxRate)-$D$47 -> 39.514081
B49: Terminal value of operations (Gordon growth) | C49: ₹ lakh | D49: =IF($D$41>$D$42,$D$48/($D$41-$D$42),NA()) -> 325.07429
B50: Own case: property market value at Y10 | C50: ₹ lakh | D50: =Inputs!$D$20*Capex!$G$28*(1+Locations!$H$21)^$D$45 -> 0
B51: less selling cost | C51: ₹ lakh | D51: =-$D$50*Inputs!$D$161 -> 0
B52: less capital-gains tax | C52: ₹ lakh | D52: =-MAX(0,$D$50+$D$51-Capex!$G$31)*Inputs!$D$162 -> 0
B53: Terminal value (operations + property) | C53: ₹ lakh | D53: =$D$49+$D$50+$D$51+$D$52 -> 325.07429
B54: Discount factor at Y10 | C54: x | D54: =1/(1+$D$41)^$D$45 -> 0.22366908
B55: Present value of terminal value | C55: ₹ lakh | D55: =$D$53*$D$54 -> 72.709066
B56: Implied EV / EBITDA of operations at Y10 | C56: x | D56: =IF(P8+Model!P124-$D$46/(1+Inputs!$D$112)>0,$D$49/(P8+Model!P124-$D$46/(1+Inputs!$D$112)),0) -> 5.5955523
B57: Cross-check: operations value at exit multiple | C57: ₹ lakh | D57: =Inputs!$D$160*(P8+Model!P124-$D$46/(1+Inputs!$D$112)) -> 290.47561
B59: Valuation results
B60: Sum of PV of FCFF, Y0-Y10 | C60: ₹ lakh | D60: =SUM($F$27:$P$27) -> 16.889041
B61: Project NPV at WACC | C61: ₹ lakh | D61: =$D$60+$D$55 -> 89.598107
B62: Terminal value share of gross value | C62: % | D62: =IF(SUM($G$27:$P$27)+$D$55<>0,$D$55/(SUM($G$27:$P$27)+$D$55),0) -> 0.42342231
B63: Project cash flows for IRR (FCFF + TV) | C63: ₹ lakh | F63: =F24+IF(F6=$D$45,$D$53,0) -> -82.1195 | G63: =G24+IF(G6=$D$45,$D$53,0) -> -6.5013466 | H63: =H24+IF(H6=$D$45,$D$53,0) -> 15.108369 | I63: =I24+IF(I6=$D$45,$D$53,0) -> 27.336694 | J63: =J24+IF(J6=$D$45,$D$53,0) -> 25.967086 | K63: =K24+IF(K6=$D$45,$D$53,0) -> 27.923707 | L63: =L24+IF(L6=$D$45,$D$53,0) -> 18.763378 | M63: =M24+IF(M6=$D$45,$D$53,0) -> 32.71158 | ... P63: =P24+IF(P6=$D$45,$D$53,0) -> 365.41894
B64: Project IRR | C64: % | D64: =IFERROR(IRR($F$63:$P$63),"n.m.") -> 0.28636431
B65: Equity view
B66: Free cash flow to equity (Y0: equity in, net of cash kept) | C66: ₹ lakh | F66: =Model!F46+Model!F49+Model!F50+Model!F51+Model!F52 -> -48.9195 | G66: =Model!G46+Model!G49+Model!G50+Model!G51+Model!G52 -> -16.029007 | H66: =Model!H46+Model!H49+Model!H50+Model!H51+Model!H52 -> 5.6699489 | I66: =Model!I46+Model!I49+Model!I50+Model!I51+Model!I52 -> 20.749943 | J66: =Model!J46+Model!J49+Model!J50+Model!J51+Model!J52 -> 19.116939 | K66: =Model!K46+Model!K49+Model!K50+Model!K51+Model!K52 -> 22.192357 | L66: =Model!L46+Model!L49+Model!L50+Model!L51+Model!L52 -> 20.88288 | M66: =Model!M46+Model!M49+Model!M50+Model!M51+Model!M52 -> 35.456165 | ... P66: =Model!P46+Model!P49+Model!P50+Model!P51+Model!P52 -> 46.589724
B67: Equity cash flows (Y10 adds TV less debt) | C67: ₹ lakh | F67: =F66+IF(F6=$D$45,$D$53-Model!F203-Model!F209,0) -> -48.9195 | G67: =G66+IF(G6=$D$45,$D$53-Model!G203-Model!G209,0) -> -16.029007 | H67: =H66+IF(H6=$D$45,$D$53-Model!H203-Model!H209,0) -> 5.6699489 | I67: =I66+IF(I6=$D$45,$D$53-Model!I203-Model!I209,0) -> 20.749943 | J67: =J66+IF(J6=$D$45,$D$53-Model!J203-Model!J209,0) -> 19.116939 | K67: =K66+IF(K6=$D$45,$D$53-Model!K203-Model!K209,0) -> 22.192357 | L67: =L66+IF(L6=$D$45,$D$53-Model!L203-Model!L209,0) -> 20.88288 | M67: =M66+IF(M6=$D$45,$D$53-Model!M203-Model!M209,0) -> 35.456165 | ... P67: =P66+IF(P6=$D$45,$D$53-Model!P203-Model!P209,0) -> 371.66401
B68: Equity IRR | C68: % | D68: =IFERROR(IRR($F$67:$P$67),"n.m.") -> 0.3293081
B69: Equity NPV at cost of equity | C69: ₹ lakh | D69: =F67+NPV($D$37,$G$67:$P$67) -> 65.839478
B70: Equity multiple (money in : money out) | C70: x | D70: =IFERROR(SUMIF($F$67:$P$67,">0")/-SUMIF($F$67:$P$67,"<0"),0) -> 8.8873609
B71: Payback
B72: Cumulative FCFF | C72: ₹ lakh | F72: =F24 -> -82.1195 | G72: =F72+G24 -> -88.620847 | H72: =G72+H24 -> -73.512477 | I72: =H72+I24 -> -46.175784 | J72: =I72+J24 -> -20.208698 | K72: =J72+K24 -> 7.7150088 | L72: =K72+L24 -> 26.478386 | M72: =L72+M24 -> 59.189967 | N72: =M72+N24 -> 94.2744 | ... P72: =O72+P24 -> 172.24732
B73: helper: payback year | C73: years | G73: =IF(AND(F72<0,G72>=0),F6+(-F72)/G24,"") | H73: =IF(AND(G72<0,H72>=0),G6+(-G72)/H24,"") | I73: =IF(AND(H72<0,I72>=0),H6+(-H72)/I24,"") | J73: =IF(AND(I72<0,J72>=0),I6+(-I72)/J24,"") | K73: =IF(AND(J72<0,K72>=0),J6+(-J72)/K24,"") -> 4.7237112 | L73: =IF(AND(K72<0,L72>=0),K6+(-K72)/L24,"") | M73: =IF(AND(L72<0,M72>=0),L6+(-L72)/M24,"") | N73: =IF(AND(M72<0,N72>=0),M6+(-M72)/N24,"") | ... P73: =IF(AND(O72<0,P72>=0),O6+(-O72)/P24,"")
B74: Cumulative PV of FCFF | C74: ₹ lakh | F74: =F27 -> -82.1195 | G74: =F74+G27 -> -87.716611 | H74: =G74+H27 -> -76.518654 | I74: =H74+I27 -> -59.07539 | J74: =I74+J27 -> -44.810593 | K74: =J74+K27 -> -31.604449 | L74: =K74+L27 -> -23.964779 | M74: =L74+M27 -> -12.498416 | N74: =M74+N27 -> -1.9107746 | ... P74: =O74+P27 -> 16.889041
B75: helper: discounted payback year | C75: years | G75: =IF(AND(F74<0,G74>=0),F6+(-F74)/G27,"") | H75: =IF(AND(G74<0,H74>=0),G6+(-G74)/H27,"") | I75: =IF(AND(H74<0,I74>=0),H6+(-H74)/I27,"") | J75: =IF(AND(I74<0,J74>=0),I6+(-I74)/J27,"") | K75: =IF(AND(J74<0,K74>=0),J6+(-J74)/K27,"") | L75: =IF(AND(K74<0,L74>=0),K6+(-K74)/L27,"") | M75: =IF(AND(L74<0,M74>=0),L6+(-L74)/M27,"") | N75: =IF(AND(M74<0,N74>=0),M6+(-M74)/N27,"") | ... P75: =IF(AND(O74<0,P74>=0),O6+(-O74)/P27,"")
B76: Payback (undiscounted, from opening) | C76: years | D76: =IF(COUNT($G$73:$P$73)=0,99,MIN($G$73:$P$73)) -> 4.7237112
B77: Discounted payback | C77: years | D77: =IF(COUNT($G$75:$P$75)=0,99,MIN($G$75:$P$75)) -> 8.1954564
B79: Key metrics
B80: Total capital requirement | C80: ₹ lakh | D80: =Capex!$G$53 -> 101.228
B81: Promoter equity | C81: ₹ lakh | D81: =Capex!$G$57 -> 68.028
B82: Term loan | C82: ₹ lakh | D82: =Capex!$G$56 -> 33.2
B83: Revenue, Y1 | C83: ₹ lakh | D83: =Model!G98 -> 104.832
B84: Revenue, Y3 (steady state) | C84: ₹ lakh | D84: =Model!I98 -> 177.8112
B85: EBITDA, Y3 | C85: ₹ lakh | D85: =Model!I29 -> 33.683883
B86: EBITDA margin, Y3 | C86: % | D86: =Model!I30 -> 0.18943623
B87: Profit after tax, Y3 | C87: ₹ lakh | D87: =Model!I38 -> 22.001296
B88: Bills per day, Y3 | C88: # | D88: =Model!I85 -> 140
B89: Break-even bills per day, Y3 | C89: # | D89: =Model!I140 -> 95.968282
B90: Margin of safety, Y3 | C90: % | D90: =Model!I141 -> 0.31451227
B91: COGS % of revenue, Y3 | C91: % | D91: =Model!I115 -> 0.29923255
B92: Staff % of revenue, Y3 | C92: % | D92: =IF(Model!I98>0,Model!I121/Model!I98,0) -> 0.25618513
B93: Occupancy % of revenue, Y3 | C93: % | D93: =IF(Model!I98>0,(Model!I122+Model!I123+Model!I124)/Model!I98,0) -> 0.088541667
B94: EBITDA, Y1 | C94: ₹ lakh | D94: =Model!G29 -> -3.722047
B95: Revenue, Y10 | C95: ₹ lakh | D95: =Model!P98 -> 297.40705
B96: EBITDA, Y10 | C96: ₹ lakh | D96: =Model!P29 -> 58.095121
B97: Peak cash-credit draw | C97: ₹ lakh | D97: =MAX(Model!$F$209:$P$209) -> 0
B98: Minimum DSCR after the ramp-up year (Y2 on) | C98: x | D98: =IF(COUNT(Model!$H$212:$P$212)=0,"n.a.",MIN(Model!$H$212:$P$212)) -> 1.851354
B99: Downside: net cash lost if shut at end of Y3 | C99: ₹ lakh | D99: =-MIN(0,I72+Inputs!$D$164*Capex!$G$48+Capex!$G$51+Model!I193+Inputs!$D$20*Capex!$G$28*(1+Locations!$H$21)^3*(1-Inputs!$D$161)) -> 19.628082 | F99: Cumulative FCFF to Y3 + equipment resale + deposit + working capital + property resale
B100: Cash at Y10 (if never distributed) | C100: ₹ lakh | D100: =Model!P58 -> 255.22602
B101: Pre-tax return on capital employed, Y5 | C101: % | D101: =IF(Model!K159+Model!K193+Model!K196>0,Model!K32/(Model!K159+Model!K193+Model!K196),0) -> 0.73062017

Sheet Scenarios
B1: Scenarios & sensitivities
B2: Live Excel data tables: each cell re-runs the full model. Keep the blue override cells at their default (0 or 1) for normal use.
B3: ="Model running: "&Inputs!$D$23 -> Model running: Prahladnagar | Rent | Toll roasting | Specialty mix | Base case
B5: Override panel (data-table input cells)
B6: Scenario (0 = Inputs; 1 Best, 2 Base, 3 Worst) | D6: 0
B7: Configuration # from Configs sheet (0 = Inputs) | D7: 0
B8: Location # (0 = Inputs/config) | D8: 0
B9: Premises # (0 = Inputs/config; 1 Rent, 2 Own) | D9: 0
B10: Roasting route # (0 = Inputs/config; 1 Buy, 2 Toll, 3 In-house) | D10: 0
B11: Bean mix # (0 = Inputs/config; 1-4) | D11: 0
B12: Wholesale kg/month at maturity (0 = Inputs) | D12: 0
B13: Bills-per-day multiplier | D13: 1
B14: Average-bill multiplier | D14: 1
B15: Rent multiplier | D15: 1
B16: Green-coffee price multiplier | D16: 1
B17: Capex multiplier | D17: 1
... B22: Tornado side (1 low, 2 high) | D22: 0
B24: Tornado definitions (one variable at a time)
B25: Variable | C25: # | D25: Low | E25: High
B26: Bills per day | C26: 1 | D26: 0.85 | E26: 1.15
B27: Average bill value | C27: 2 | D27: 0.9 | E27: 1.1
B28: Rent | C28: 3 | D28: 0.8 | E28: 1.2
B29: Green-coffee price | C29: 4 | D29: 0.7 | E29: 1.3
B30: Capex | C30: 5 | D30: 0.85 | E30: 1.2
B31: Staff cost | C31: 6 | D31: 0.9 | E31: 1.15
B32: WACC (+/- pp) | C32: 7 | D32: -0.02 | E32: 0.02
B33: Terminal growth (abs.) | C33: 8 | D33: 0.03 | E33: 0.05
B35: Effective values used by the model
B36: Bills-per-day multiplier | C36: x | D36: =$D$13*IF(AND($D$21=1,$D$22>0),CHOOSE($D$22,$D$26,$E$26),1) -> 1
B37: Average-bill multiplier | C37: x | D37: =$D$14*IF(AND($D$21=2,$D$22>0),CHOOSE($D$22,$D$27,$E$27),1) -> 1
B38: Rent multiplier | C38: x | D38: =$D$15*IF(AND($D$21=3,$D$22>0),CHOOSE($D$22,$D$28,$E$28),1) -> 1
B39: Green-price multiplier | C39: x | D39: =$D$16*IF(AND($D$21=4,$D$22>0),CHOOSE($D$22,$D$29,$E$29),1) -> 1
B40: Capex multiplier | C40: x | D40: =$D$17*IF(AND($D$21=5,$D$22>0),CHOOSE($D$22,$D$30,$E$30),1) -> 1
B41: Staff-cost multiplier | C41: x | D41: =$D$18*IF(AND($D$21=6,$D$22>0),CHOOSE($D$22,$D$31,$E$31),1) -> 1
B42: Wholesale kg/month at maturity | C42: kg | D42: =IF($D$12>0,$D$12,Inputs!$D$57) -> 150
B43: WACC change | C43: pp | D43: =$D$19+IF(AND($D$21=7,$D$22>0),CHOOSE($D$22,$D$32,$E$32),0) -> 0
B44: Terminal growth | C44: % | D44: =IF(AND($D$21=8,$D$22>0),CHOOSE($D$22,$D$33,$E$33),IF($D$20>0,$D$20,Inputs!$D$159)) -> 0.04
B46: T1. Scenario analysis (Best / Base / Worst) for the active configuration
B47: Scenario | D47: NPV ₹ lakh | E47: Project IRR | F47: Equity IRR | G47: Equity NPV ₹ lakh | H47: Payback | I47: Disc. payback | J47: Capital need ₹ lakh | K47: Y3 revenue ₹ lakh | L47: Y3 EBITDA margin | M47: Break-even bills/day | N47: Peak cash credit ₹ lakh
B48: Current model value → | D48: =DCF!$D$61 -> 89.598107 | E48: =DCF!$D$64 -> 0.28636431 | F48: =DCF!$D$68 -> 0.3293081 | G48: =DCF!$D$69 -> 65.839478 | H48: =DCF!$D$76 -> 4.7237112 | I48: =DCF!$D$77 -> 8.1954564 | J48: =DCF!$D$80 -> 101.228 | K48: =DCF!$D$84 -> 177.8112 | L48: =DCF!$D$86 -> 0.18943623 | M48: =DCF!$D$89 -> 95.968282 | N48: =DCF!$D$97 -> 0
B49: Best | C49: 1 | D49: 289.26486 | E49: 0.49305477 | F49: 0.60776261 | G49: 233.6849 | H49: 2.8168019 | I49: 3.7503895 | J49: 98.063 | K49: 208.39634 | L49: 0.24432326 | M49: 96.830504 | N49: 0
B50: Base | C50: 2 | D50: 89.598107 | E50: 0.28636431 | F50: 0.3293081 | G50: 65.839478 | H50: 4.7237112 | I50: 8.1954564 | J50: 101.228 | K50: 177.8112 | L50: 0.18943623 | M50: 95.968282 | N50: 0
B51: Worst | C51: 3 | D51: -187.27283 | E51: n.m. | F51: n.m. | G51: -138.30884 | H51: 99 | I51: 99 | J51: 107.558 | K51: 124.66879 | L51: -0.01130869 | M51: 103.00202 | N51: 282.65963
B53: T2. Location × premises (active roasting route, mix and scenario)
B54: Project NPV, ₹ lakh
B55: Location ↓ Premises → | D55: Rent | E55: Own
B56: Current model value → | C56: =DCF!$D$61 -> 89.598107 | D56: 1 | E56: 2
B57: Prahladnagar | C57: 1 | D57: 89.598107 | E57: 84.795799
B58: Sindhu Bhavan Road | C58: 2 | D58: 192.74367 | E58: 223.51428
B59: GIFT City | C59: 3 | D59: 148.34342 | E59: 184.89171
B60: Sanand | C60: 4 | D60: -10.181679 | E60: -6.7925228
B61: Project IRR
B62: Location ↓ Premises → | D62: Rent | E62: Own
B63: Current model value → | C63: =DCF!$D$64 -> 0.28636431 | D63: 1 | E63: 2
B64: Prahladnagar | C64: 1 | D64: 0.28636431 | E64: 0.18943528
B65: Sindhu Bhavan Road | C65: 2 | D65: 0.35188142 | E65: 0.21696549
B66: GIFT City | C66: 3 | D66: 0.34245462 | E66: 0.24944395
B67: Sanand | C67: 4 | D67: 0.14206067 | E67: 0.14098613
B68: Equity IRR
B69: Location ↓ Premises → | D69: Rent | E69: Own
B70: Current model value → | C70: =DCF!$D$68 -> 0.3293081 | D70: 1 | E70: 2
B71: Prahladnagar | C71: 1 | D71: 0.3293081 | E71: 0.24302537
B72: Sindhu Bhavan Road | C72: 2 | D72: 0.40699885 | E72: 0.28445554
B73: GIFT City | C73: 3 | D73: 0.39295906 | E73: 0.32562288
B74: Sanand | C74: 4 | D74: 0.15840147 | E74: 0.17019249
B75: Total capital requirement, ₹ lakh
B76: Location ↓ Premises → | D76: Rent | E76: Own
B77: Current model value → | C77: =DCF!$D$80 -> 101.228 | D77: 1 | E77: 2
B78: Prahladnagar | C78: 1 | D78: 101.228 | E78: 277.1655
B79: Sindhu Bhavan Road | C79: 2 | D79: 129.8836 | E79: 413.3356
B80: GIFT City | C80: 3 | D80: 97.5531 | E80: 220.7946
B81: Sanand | C81: 4 | D81: 87.2162 | E81: 152.4137
B83: T3. Roasting route × bean mix (active location, premises and scenario)
B84: Project NPV, ₹ lakh
B85: Roasting ↓ Mix → | D85: Value | E85: Specialty | F85: Premium | G85: Custom
B86: Current model value → | C86: =DCF!$D$61 -> 89.598107 | D86: 1 | E86: 2 | F86: 3 | G86: 4
B87: Buy roasted | C87: 1 | D87: 37.042675 | E87: 64.417634 | F87: 53.431233 | G87: 72.750112
B88: Toll roasting | C88: 2 | D88: 53.565401 | E88: 89.598107 | F88: 80.62891 | G88: 99.827748
B89: In-house roastery | C89: 3 | D89: 2.1925082 | E89: 39.977441 | F89: 54.67342 | G89: 56.410678
B90: EBITDA margin, Y3
B91: Roasting ↓ Mix → | D91: Value | E91: Specialty | F91: Premium | G91: Custom
B92: Current model value → | C92: =DCF!$D$86 -> 0.18943623 | D92: 1 | E92: 2 | F92: 3 | G92: 4
B93: Buy roasted | C93: 1 | D93: 0.15220503 | E93: 0.16825395 | F93: 0.15175521 | G93: 0.17219924
B94: Toll roasting | C94: 2 | D94: 0.16660255 | E94: 0.18943623 | F94: 0.17490395 | G94: 0.19467439
B95: In-house roastery | C95: 3 | D95: 0.12209632 | E95: 0.13699142 | F95: 0.12987248 | G95: 0.14308084
B97: T4. Configurations (defined on the Configs sheet), active scenario
B98: Configuration | D98: NPV ₹ lakh | E98: Project IRR | F98: Equity IRR | G98: Payback | H98: Capital need ₹ lakh | I98: Equity ₹ lakh | J98: Y3 revenue ₹ lakh | K98: Y3 EBITDA ₹ lakh | L98: Y3 EBITDA margin | M98: Break-even bills/day | N98: Min DSCR
B99: Current model value → | D99: =DCF!$D$61 -> 89.598107 | E99: =DCF!$D$64 -> 0.28636431 | F99: =DCF!$D$68 -> 0.3293081 | G99: =DCF!$D$76 -> 4.7237112 | H99: =DCF!$D$80 -> 101.228 | I99: =DCF!$D$81 -> 68.028 | J99: =DCF!$D$84 -> 177.8112 | K99: =DCF!$D$85 -> 33.683883 | L99: =DCF!$D$86 -> 0.18943623 | M99: =DCF!$D$89 -> 95.968282 | N99: =DCF!$D$98 -> 1.851354
B100: =Configs!$C$6 -> PN-R-Buy | C100: 1 | D100: 64.417634 | E100: 0.25633306 | F100: 0.29287169 | G100: 5.2878127 | H100: 101.228 | I100: 68.028 | J100: 177.8112 | K100: 29.917437 | L100: 0.16825395 | M100: 99.46631 | N100: 1.5157055
B101: =Configs!$C$7 -> PN-R-Toll | C101: 2 | D101: 89.598107 | E101: 0.28636431 | F101: 0.3293081 | G101: 4.7237112 | H101: 101.228 | I101: 68.028 | J101: 177.8112 | K101: 33.683883 | L101: 0.18943623 | M101: 95.968282 | N101: 1.851354
B102: =Configs!$C$8 -> PN-R-InH | C102: 3 | D102: 39.977441 | E102: 0.20926158 | F102: 0.23621059 | G102: 6.8250334 | H102: 122.37925 | I102: 80.27925 | J102: 206.58645 | K102: 28.300571 | L102: 0.13699142 | M102: 104.24571 | N102: 0.87394361
B103: =Configs!$C$9 -> PN-O-Toll | C103: 4 | D103: 84.795799 | E103: 0.18943528 | F103: 0.24302537 | G103: 7.4757957 | H103: 277.1655 | I103: 125.5655 | J103: 177.8112 | K103: 48.512508 | L103: 0.27283156 | M103: 76.58424 | N103: 1.0589273
B104: =Configs!$C$10 -> PN-R-Toll-Val | C104: 5 | D104: 53.565401 | E104: 0.24235897 | F104: 0.27586633 | G104: 5.7474736 | H104: 101.228 | I104: 68.028 | J104: 168.03158 | K104: 27.994491 | L104: 0.16660255 | M104: 106.87068 | N104: 1.4341188
B105: =Configs!$C$11 -> PN-R-Toll-Prm | C105: 6 | D105: 80.62891 | E105: 0.27346366 | F105: 0.31260033 | G105: 5.0096277 | H105: 101.228 | I105: 68.028 | J105: 177.36667 | K105: 31.022132 | L105: 0.17490395 | M105: 93.493484 | N105: 1.5849419
B106: =Configs!$C$12 -> PN-R-Toll-Cus | C106: 7 | D106: 99.827748 | E106: 0.29823094 | F106: 0.34411869 | G106: 4.5563681 | H106: 101.228 | I106: 68.028 | J106: 181.36742 | K106: 35.307592 | L106: 0.19467439 | M106: 94.53505 | N106: 1.9865789
B107: =Configs!$C$13 -> SBR-R-Buy | C107: 8 | D107: 158.05882 | E107: 0.32457998 | F107: 0.37333049 | G107: 4.2548712 | H107: 129.8836 | I107: 90.1836 | J107: 245.3379 | K107: 49.712034 | L107: 0.2026268 | M107: 113.47046 | N107: 2.3858199
B108: =Configs!$C$14 -> SBR-R-Toll | C108: 9 | D108: 192.74367 | E108: 0.35188142 | F108: 0.40699885 | G108: 3.9742689 | H108: 129.8836 | I108: 90.1836 | J108: 245.3379 | K108: 54.90885 | L108: 0.22380908 | M108: 109.58519 | N108: 2.7400617
B109: =Configs!$C$15 -> SBR-R-InH | C109: 10 | D109: 140.0069 | E109: 0.28330171 | F109: 0.32139785 | G109: 4.9965376 | H109: 153.00435 | I109: 104.10435 | J109: 274.11315 | K109: 49.037739 | L109: 0.17889597 | M109: 117.81229 | N109: 1.7083054
B110: =Configs!$C$16 -> SBR-O-Toll | C110: 11 | D110: 223.51428 | E110: 0.21696549 | F110: 0.28445554 | G110: 6.7059271 | H110: 413.3356 | I110: 181.8356 | J110: 245.3379 | K110: 82.16265 | L110: 0.33489587 | M110: 78.752628 | N110: 1.2692348
B111: =Configs!$C$17 -> SBR-R-Toll-Cus | C111: 12 | D111: 207.16774 | E111: 0.36321743 | F111: 0.42150821 | G111: 3.8518111 | H111: 129.8836 | I111: 90.1836 | J111: 250.24466 | K111: 57.208806 | L111: 0.2286115 | M111: 107.94935 | N111: 2.8995161
...

Sheet Configs
B1: Configurations compared
B2: Edit the blue cells to define your own combinations. Results come from data table T4 on the Scenarios sheet (active scenario).
B3: ="Model running: "&Inputs!$D$23 -> Model running: Prahladnagar | Rent | Toll roasting | Specialty mix | Base case
B5: # | C5: Name | D5: Location | E5: Premises | F5: Roasting | G5: Mix | I5: NPV ₹ lakh | J5: Project IRR | K5: Equity IRR | L5: Payback | M5: Capital ₹ lakh | N5: Y3 EBITDA % | O5: Break-even bills | P5: Rank (NPV)
B6: 1 | C6: PN-R-Buy | D6: Prahladnagar | E6: Rent | F6: Buy roasted | G6: Specialty | I6: =Scenarios!$D$100 -> 0 | J6: =Scenarios!$E$100 -> 0 | K6: =Scenarios!$F$100 -> 0 | L6: =Scenarios!$G$100 -> 0 | M6: =Scenarios!$H$100 -> 0 | N6: =Scenarios!$L$100 -> 0 | O6: =Scenarios!$M$100 -> 0 | P6: =RANK(I6,$I$6:$I$25) -> 1
B7: 2 | C7: PN-R-Toll | D7: Prahladnagar | E7: Rent | F7: Toll roasting | G7: Specialty | I7: =Scenarios!$D$101 -> 0 | J7: =Scenarios!$E$101 -> 0 | K7: =Scenarios!$F$101 -> 0 | L7: =Scenarios!$G$101 -> 0 | M7: =Scenarios!$H$101 -> 0 | N7: =Scenarios!$L$101 -> 0 | O7: =Scenarios!$M$101 -> 0 | P7: =RANK(I7,$I$6:$I$25) -> 1
B8: 3 | C8: PN-R-InH | D8: Prahladnagar | E8: Rent | F8: In-house roastery | G8: Specialty | I8: =Scenarios!$D$102 -> 0 | J8: =Scenarios!$E$102 -> 0 | K8: =Scenarios!$F$102 -> 0 | L8: =Scenarios!$G$102 -> 0 | M8: =Scenarios!$H$102 -> 0 | N8: =Scenarios!$L$102 -> 0 | O8: =Scenarios!$M$102 -> 0 | P8: =RANK(I8,$I$6:$I$25) -> 1
B9: 4 | C9: PN-O-Toll | D9: Prahladnagar | E9: Own | F9: Toll roasting | G9: Specialty | I9: =Scenarios!$D$103 -> 0 | J9: =Scenarios!$E$103 -> 0 | K9: =Scenarios!$F$103 -> 0 | L9: =Scenarios!$G$103 -> 0 | M9: =Scenarios!$H$103 -> 0 | N9: =Scenarios!$L$103 -> 0 | O9: =Scenarios!$M$103 -> 0 | P9: =RANK(I9,$I$6:$I$25) -> 1
B10: 5 | C10: PN-R-Toll-Val | D10: Prahladnagar | E10: Rent | F10: Toll roasting | G10: Value | I10: =Scenarios!$D$104 -> 0 | J10: =Scenarios!$E$104 -> 0 | K10: =Scenarios!$F$104 -> 0 | L10: =Scenarios!$G$104 -> 0 | M10: =Scenarios!$H$104 -> 0 | N10: =Scenarios!$L$104 -> 0 | O10: =Scenarios!$M$104 -> 0 | P10: =RANK(I10,$I$6:$I$25) -> 1
B11: 6 | C11: PN-R-Toll-Prm | D11: Prahladnagar | E11: Rent | F11: Toll roasting | G11: Premium | I11: =Scenarios!$D$105 -> 0 | J11: =Scenarios!$E$105 -> 0 | K11: =Scenarios!$F$105 -> 0 | L11: =Scenarios!$G$105 -> 0 | M11: =Scenarios!$H$105 -> 0 | N11: =Scenarios!$L$105 -> 0 | O11: =Scenarios!$M$105 -> 0 | P11: =RANK(I11,$I$6:$I$25) -> 1
B12: 7 | C12: PN-R-Toll-Cus | D12: Prahladnagar | E12: Rent | F12: Toll roasting | G12: Custom | I12: =Scenarios!$D$106 -> 0 | J12: =Scenarios!$E$106 -> 0 | K12: =Scenarios!$F$106 -> 0 | L12: =Scenarios!$G$106 -> 0 | M12: =Scenarios!$H$106 -> 0 | N12: =Scenarios!$L$106 -> 0 | O12: =Scenarios!$M$106 -> 0 | P12: =RANK(I12,$I$6:$I$25) -> 1
B13: 8 | C13: SBR-R-Buy | D13: Sindhu Bhavan Road | E13: Rent | F13: Buy roasted | G13: Specialty | I13: =Scenarios!$D$107 -> 0 | J13: =Scenarios!$E$107 -> 0 | K13: =Scenarios!$F$107 -> 0 | L13: =Scenarios!$G$107 -> 0 | M13: =Scenarios!$H$107 -> 0 | N13: =Scenarios!$L$107 -> 0 | O13: =Scenarios!$M$107 -> 0 | P13: =RANK(I13,$I$6:$I$25) -> 1
B14: 9 | C14: SBR-R-Toll | D14: Sindhu Bhavan Road | E14: Rent | F14: Toll roasting | G14: Specialty | I14: =Scenarios!$D$108 -> 0 | J14: =Scenarios!$E$108 -> 0 | K14: =Scenarios!$F$108 -> 0 | L14: =Scenarios!$G$108 -> 0 | M14: =Scenarios!$H$108 -> 0 | N14: =Scenarios!$L$108 -> 0 | O14: =Scenarios!$M$108 -> 0 | P14: =RANK(I14,$I$6:$I$25) -> 1
B15: 10 | C15: SBR-R-InH | D15: Sindhu Bhavan Road | E15: Rent | F15: In-house roastery | G15: Specialty | I15: =Scenarios!$D$109 -> 0 | J15: =Scenarios!$E$109 -> 0 | K15: =Scenarios!$F$109 -> 0 | L15: =Scenarios!$G$109 -> 0 | M15: =Scenarios!$H$109 -> 0 | N15: =Scenarios!$L$109 -> 0 | O15: =Scenarios!$M$109 -> 0 | P15: =RANK(I15,$I$6:$I$25) -> 1
B16: 11 | C16: SBR-O-Toll | D16: Sindhu Bhavan Road | E16: Own | F16: Toll roasting | G16: Specialty | I16: =Scenarios!$D$110 -> 0 | J16: =Scenarios!$E$110 -> 0 | K16: =Scenarios!$F$110 -> 0 | L16: =Scenarios!$G$110 -> 0 | M16: =Scenarios!$H$110 -> 0 | N16: =Scenarios!$L$110 -> 0 | O16: =Scenarios!$M$110 -> 0 | P16: =RANK(I16,$I$6:$I$25) -> 1
B17: 12 | C17: SBR-R-Toll-Cus | D17: Sindhu Bhavan Road | E17: Rent | F17: Toll roasting | G17: Custom | I17: =Scenarios!$D$111 -> 0 | J17: =Scenarios!$E$111 -> 0 | K17: =Scenarios!$F$111 -> 0 | L17: =Scenarios!$G$111 -> 0 | M17: =Scenarios!$H$111 -> 0 | N17: =Scenarios!$L$111 -> 0 | O17: =Scenarios!$M$111 -> 0 | P17: =RANK(I17,$I$6:$I$25) -> 1
B18: 13 | C18: GIFT-R-Buy | D18: GIFT City | E18: Rent | F18: Buy roasted | G18: Specialty | I18: =Scenarios!$D$112 -> 0 | J18: =Scenarios!$E$112 -> 0 | K18: =Scenarios!$F$112 -> 0 | L18: =Scenarios!$G$112 -> 0 | M18: =Scenarios!$H$112 -> 0 | N18: =Scenarios!$L$112 -> 0 | O18: =Scenarios!$M$112 -> 0 | P18: =RANK(I18,$I$6:$I$25) -> 1
B19: 14 | C19: GIFT-R-Toll | D19: GIFT City | E19: Rent | F19: Toll roasting | G19: Specialty | I19: =Scenarios!$D$113 -> 0 | J19: =Scenarios!$E$113 -> 0 | K19: =Scenarios!$F$113 -> 0 | L19: =Scenarios!$G$113 -> 0 | M19: =Scenarios!$H$113 -> 0 | N19: =Scenarios!$L$113 -> 0 | O19: =Scenarios!$M$113 -> 0 | P19: =RANK(I19,$I$6:$I$25) -> 1
B20: 15 | C20: GIFT-R-InH | D20: GIFT City | E20: Rent | F20: In-house roastery | G20: Specialty | I20: =Scenarios!$D$114 -> 0 | J20: =Scenarios!$E$114 -> 0 | K20: =Scenarios!$F$114 -> 0 | L20: =Scenarios!$G$114 -> 0 | M20: =Scenarios!$H$114 -> 0 | N20: =Scenarios!$L$114 -> 0 | O20: =Scenarios!$M$114 -> 0 | P20: =RANK(I20,$I$6:$I$25) -> 1
B21: 16 | C21: GIFT-O-Toll | D21: GIFT City | E21: Own | F21: Toll roasting | G21: Specialty | I21: =Scenarios!$D$115 -> 0 | J21: =Scenarios!$E$115 -> 0 | K21: =Scenarios!$F$115 -> 0 | L21: =Scenarios!$G$115 -> 0 | M21: =Scenarios!$H$115 -> 0 | N21: =Scenarios!$L$115 -> 0 | O21: =Scenarios!$M$115 -> 0 | P21: =RANK(I21,$I$6:$I$25) -> 1
B22: 17 | C22: GIFT-R-Toll-Cus | D22: GIFT City | E22: Rent | F22: Toll roasting | G22: Custom | I22: =Scenarios!$D$116 -> 0 | J22: =Scenarios!$E$116 -> 0 | K22: =Scenarios!$F$116 -> 0 | L22: =Scenarios!$G$116 -> 0 | M22: =Scenarios!$H$116 -> 0 | N22: =Scenarios!$L$116 -> 0 | O22: =Scenarios!$M$116 -> 0 | P22: =RANK(I22,$I$6:$I$25) -> 1
B23: 18 | C23: SAN-R-Toll | D23: Sanand | E23: Rent | F23: Toll roasting | G23: Specialty | I23: =Scenarios!$D$117 -> 0 | J23: =Scenarios!$E$117 -> 0 | K23: =Scenarios!$F$117 -> 0 | L23: =Scenarios!$G$117 -> 0 | M23: =Scenarios!$H$117 -> 0 | N23: =Scenarios!$L$117 -> 0 | O23: =Scenarios!$M$117 -> 0 | P23: =RANK(I23,$I$6:$I$25) -> 1
B24: 19 | C24: SAN-R-InH | D24: Sanand | E24: Rent | F24: In-house roastery | G24: Specialty | I24: =Scenarios!$D$118 -> 0 | J24: =Scenarios!$E$118 -> 0 | K24: =Scenarios!$F$118 -> 0 | L24: =Scenarios!$G$118 -> 0 | M24: =Scenarios!$H$118 -> 0 | N24: =Scenarios!$L$118 -> 0 | O24: =Scenarios!$M$118 -> 0 | P24: =RANK(I24,$I$6:$I$25) -> 1
B25: 20 | C25: SAN-O-Toll | D25: Sanand | E25: Own | F25: Toll roasting | G25: Specialty | I25: =Scenarios!$D$119 -> 0 | J25: =Scenarios!$E$119 -> 0 | K25: =Scenarios!$F$119 -> 0 | L25: =Scenarios!$G$119 -> 0 | M25: =Scenarios!$H$119 -> 0 | N25: =Scenarios!$L$119 -> 0 | O25: =Scenarios!$M$119 -> 0 | P25: =RANK(I25,$I$6:$I$25) -> 1
B27: Naming: PN = Prahladnagar, SBR = Sindhu Bhavan Road, GIFT = GIFT City, SAN = Sanand; R = rent, O = own; Buy / Toll / InH = roasting route; Val / Prm = Value / Premium mix (default Specialty).

Sheet Sources
B1: Sources
B2: Evidence behind the main assumptions (gathered October 2026). Estimates without a public source are flagged as judgement in the notes columns.
B3: ="Model running: "&Inputs!$D$23 -> Model running: Prahladnagar | Rent | Toll roasting | Specialty mix | Base case
B5: Topic | C5: What was used | D5: Source
B6: Rents, Prahladnagar | C6: 99acres / MagicBricks / housing.com listings, Oct 2026: ₹55-120 per sqft per month (Titanium Heights, Corporate Road) | D6: https://www.99acres.com
B7: Rents, Sindhu Bhavan Road | C7: 99acres F&B shop 495 sqft ₹1.08 lakh (~₹218/sqft); otloo Time Square-2 2,651 sqft ₹2.25 lakh | D7: https://www.99acres.com
B8: Purchase prices | C8: MagicBricks: SBR showroom ₹19,500/sqft; Prahladnagar ₹5,560-9,626/sqft (offices) | D8: https://www.magicbricks.com
B9: GIFT City | C9: 99acres coffee shop ₹1 lakh/month; GIFT City RFPs for café/food zone (2026) | D9: https://www.giftgujarat.in
B10: Sanand | C10: Micron Sanand ATMP opened 28 Feb 2026 (~US$2.75 bn); 6 ISM projects in Gujarat, ~50,000 jobs (ET, Aug 2026) | D10: https://investors.micron.com
B11: Espresso machines | C11: West End Coffee price comparison: La Marzocco Linea PB 2GR ₹11.26 lakh + GST | D11: https://westendcoffee.co
B12: Roasters | C12: Aaroasta (Rajkot) drum roasters 0.5-50 kg | D12: https://aaroasta.com
B13: Electricity | C13: Torrent Power Ahmedabad tariff FY2026-27, non-RGP commercial 455 paise/unit + charges | D13: https://www.torrentpower.com
B14: Wages | C14: Gujarat minimum wages from 1 Apr 2026; Indeed/ERI barista pay in Ahmedabad | D14: https://in.indeed.com
B15: Risk-free rate & policy rate | C15: India 10-yr G-sec 7.29% (8 Oct 2026); RBI repo 5.50% | D15: https://tradingeconomics.com/india/government-bond-yield
B16: Equity risk premium | C16: Damodaran, Country risk premiums, Jan 2026 (India: ERP 7.08%, CRP 2.85%) | D16: https://pages.stern.nyu.edu/~adamodar/
... B18: Chain economics | C18: Tata Starbucks FY25 revenue ₹1,277 cr (~₹2.7 cr per store); Blue Tokai, Third Wave filings | D18: https://www.worldcoffeeportal.com
B19: Aggregator fees | C19: Swiggy/Zomato effective commission ~24-30% incl. GST & discounts (2026 reports)
B20: Coffee prices | C20: Coffee Board of India; USDA FAS India Coffee Annual (May 2026); ICE Coffee C ~285 c/lb (9 Oct 2026) | D20: https://www.fas.usda.gov
B21: Tax | C21: Income-tax Act s.115BAA (25.168%), depreciation block rates (Appendix I) | D21: https://incometaxindia.gov.in
